{"rss": {"@version": "5.1", "list": {"@page": "1259", "@pagecount": "1546", "@pagesize": "40", "@recordcount": "61832", "video": [{"last": "2020-04-29 00:02:54", "id": "84708", "tid": "13", "name": "剑魔独孤求败粤语", "type": "香港剧", "pic": "https://tu.tianzuida.com/pic/upload/vod/2020-04-29/1588089774.jpg", "lang": "粤语", "area": "香港", "year": "1990", "state": "0", "note": "21集全", "actor": "黄日华,文雪儿,邵美琪,蔡嘉莉,吴岱融,郑艳凤,李丽丽,罗乐林,刘家辉", "director": "庄伟健", "dl": {"dd": {"@flag": "zuidam3u8", "#text": "第01集$http://mojing.huoyanzuida.com/20200428/2852_22488f1b/index.m3u8$zuidam3u8#第02集$http://mojing.huoyanzuida.com/20200428/2853_ffc48e84/index.m3u8$zuidam3u8#第03集$http://mojing.huoyanzuida.com/20200428/2854_2694ada2/index.m3u8$zuidam3u8#第04集$http://mojing.huoyanzuida.com/20200428/2855_70e7dbb3/index.m3u8$zuidam3u8#第05集$http://mojing.huoyanzuida.com/20200428/2856_efd3e318/index.m3u8$zuidam3u8#第06集$http://mojing.huoyanzuida.com/20200428/2857_fcd52d35/index.m3u8$zuidam3u8#第07集$http://mojing.huoyanzuida.com/20200428/2858_591a4943/index.m3u8$zuidam3u8#第08集$http://mojing.huoyanzuida.com/20200428/2859_40e4175f/index.m3u8$zuidam3u8#第09集$http://mojing.huoyanzuida.com/20200428/2860_72070a39/index.m3u8$zuidam3u8#第10集$http://mojing.huoyanzuida.com/20200428/2862_9736cd0f/index.m3u8$zuidam3u8#第11集$http://mojing.huoyanzuida.com/20200428/2861_dbe19bd4/index.m3u8$zuidam3u8#第12集$http://mojing.huoyanzuida.com/20200428/2863_06e70410/index.m3u8$zuidam3u8#第13集$http://mojing.huoyanzuida.com/20200428/2864_02dff88a/index.m3u8$zuidam3u8#第14集$http://mojing.huoyanzuida.com/20200428/2866_948995a1/index.m3u8$zuidam3u8#第15集$http://mojing.huoyanzuida.com/20200428/2865_89a03483/index.m3u8$zuidam3u8#第16集$http://mojing.huoyanzuida.com/20200428/2867_3046b96f/index.m3u8$zuidam3u8#第17集$http://mojing.huoyanzuida.com/20200428/2868_06f09863/index.m3u8$zuidam3u8#第18集$http://mojing.huoyanzuida.com/20200428/2869_1a37bf2a/index.m3u8$zuidam3u8#第19集$http://mojing.huoyanzuida.com/20200428/2870_531a9eb3/index.m3u8$zuidam3u8#第20集$http://mojing.huoyanzuida.com/20200428/2871_559b2db3/index.m3u8$zuidam3u8#第21集$http://mojing.huoyanzuida.com/20200428/2872_88ce305b/index.m3u8$zuidam3u8"}}, "des": "天峰（罗乐林 饰）和严晓青（李丽丽 饰）是一对江湖夫妻，因为作恶多端而遭到了名门正派的追杀，最终，两人不敌对手落败，天峰遭到了囚禁，而严晓青则隐姓埋名流落民间。林康（黄日华 饰）是两人的孩子，父母落难之时他尚且年幼，被一农夫收养，一晃眼几十年过去，林康成长为了铿锵男儿，继承了父亲卓绝的武功。 那边厢，天峰好不容易逃脱了囹圄，和严晓青重逢，两人组建了天圣教，开始了他们的复仇。面对这支异军突起，正义满满的林康自然要带领着武林志士们奋勇反击，殊不知，他视为死敌的天峰和严晓青，正是他的亲生父母。"}, {"last": "2020-04-29 00:11:15", "id": "84709", "tid": "13", "name": "回到唐山粤语", "type": "香港剧", "pic": "https://tu.tianzuida.com/pic/upload/vod/2020-04-29/202004291588090249.jpg", "lang": "粤语", "area": "香港", "year": "1989", "state": "0", "note": "20集全", "actor": "黎明,黎美娴,罗嘉良,刘美娟,夏雨,戴志伟", "director": "梅小青", "dl": {"dd": {"@flag": "zuidam3u8", "#text": "第01集$http://mojing.huoyanzuida.com/20200428/2813_d87d32fc/index.m3u8$zuidam3u8#第02集$http://mojing.huoyanzuida.com/20200428/2814_7a00c5cd/index.m3u8$zuidam3u8#第03集$http://mojing.huoyanzuida.com/20200428/2812_35767ac0/index.m3u8$zuidam3u8#第04集$http://mojing.huoyanzuida.com/20200428/2873_57cf1995/index.m3u8$zuidam3u8#第05集$http://mojing.huoyanzuida.com/20200428/2815_ef0a9848/index.m3u8$zuidam3u8#第06集$http://mojing.huoyanzuida.com/20200428/2816_1cb8dd19/index.m3u8$zuidam3u8#第07集$http://mojing.huoyanzuida.com/20200428/2874_f0a36636/index.m3u8$zuidam3u8#第08集$http://mojing.huoyanzuida.com/20200428/2818_feba0bfd/index.m3u8$zuidam3u8#第09集$http://mojing.huoyanzuida.com/20200428/2817_0be1c4da/index.m3u8$zuidam3u8#第10集$http://mojing.huoyanzuida.com/20200428/2820_d6069fcf/index.m3u8$zuidam3u8#第11集$http://mojing.huoyanzuida.com/20200428/2819_cc6dac7c/index.m3u8$zuidam3u8#第12集$http://mojing.huoyanzuida.com/20200428/2823_eb3c5013/index.m3u8$zuidam3u8#第13集$http://mojing.huoyanzuida.com/20200428/2821_e510a95e/index.m3u8$zuidam3u8#第14集$http://mojing.huoyanzuida.com/20200428/2822_ea4addec/index.m3u8$zuidam3u8#第15集$http://mojing.huoyanzuida.com/20200428/2824_13ac30ef/index.m3u8$zuidam3u8#第16集$http://mojing.huoyanzuida.com/20200428/2828_6f6e4aa7/index.m3u8$zuidam3u8#第17集$http://mojing.huoyanzuida.com/20200428/2825_184b6fc0/index.m3u8$zuidam3u8#第18集$http://mojing.huoyanzuida.com/20200428/2826_772b2781/index.m3u8$zuidam3u8#第19集$http://mojing.huoyanzuida.com/20200428/2827_dc1e5541/index.m3u8$zuidam3u8#第20集$http://mojing.huoyanzuida.com/20200428/2831_65f592cd/index.m3u8$zuidam3u8"}}, "des": "这天是镇上的大财主徐旺财（夏雨）做大寿的日子，是夜，白小娜（黎美娴）拿豆腐送上徐家，在大厅遇上大家在帮徐旺财庆生，有人送寿包来，白小娜好奇的问：有寿包，哪寿衣呢？即时大家都说：啜啜啜。。。，徐旺财说： 你真是的。徐旺财有俩个老婆，大老婆婉君（韩马利）温柔贤惠，有子徐又富（罗嘉良）也是为人温顺。婉君对小老婆(许逸华）也是平起平坐的态度，从不对她刻薄。小老婆徐逸华（不确定是不是这个名字）本性‘吧辣’有女陈嘉贤性格刁蛮粗鲁帮夏雨（徐旺财）打理生意：赌场，鸦片（好像是）。当晚有山贼侵入镇，来到夏雨（徐旺财）家刚好黎美娴（白小娜）正在好奇的问：有寿包，哪寿衣呢？即时大家都说：啜啜啜。。。，夏雨（徐旺财）说： 你真是的时，山贼闯入同时挟持了黎美娴（白小娜）与罗嘉良（徐又富）。要夏雨（徐旺财）拿钱换。就把他们带回山上。 电视剧《回到唐山》出品于1989年，是一部民初的轻喜剧。当年在东南亚一带播放时曾轰动一时，以致于无线在1990年又拿回本港重播，也是黎明在TVB时期少有的喜剧作品，女主角则是当时正当红的无线花旦黎美娴。"}, {"last": "2020-04-29 00:19:13", "id": "84710", "tid": "13", "name": "庙街妈兄弟粤语", "type": "香港剧", "pic": "https://tu.tianzuida.com/pic/upload/vod/2020-04-29/202004291588090734.jpg", "lang": "粤语", "area": "香港", "year": "2000", "state": "0", "note": "22集全", "actor": "李克勤,梁汉文,黄淑仪,叶璇,刘江", "director": "潘嘉德", "dl": {"dd": {"@flag": "zuidam3u8", "#text": "第01集$http://mojing.huoyanzuida.com/20200428/2829_0ae79583/index.m3u8$zuidam3u8#第02集$http://mojing.huoyanzuida.com/20200428/2830_96b3baea/index.m3u8$zuidam3u8#第03集$http://mojing.huoyanzuida.com/20200428/2838_88ab8a93/index.m3u8$zuidam3u8#第04集$http://mojing.huoyanzuida.com/20200428/2832_91327133/index.m3u8$zuidam3u8#第05集$http://mojing.huoyanzuida.com/20200428/2833_de0a1bea/index.m3u8$zuidam3u8#第06集$http://mojing.huoyanzuida.com/20200428/2840_d8ffdcca/index.m3u8$zuidam3u8#第07集$http://mojing.huoyanzuida.com/20200428/2834_9965a4f7/index.m3u8$zuidam3u8#第08集$http://mojing.huoyanzuida.com/20200428/2835_4283059d/index.m3u8$zuidam3u8#第09集$http://mojing.huoyanzuida.com/20200428/2836_f0bc2ab5/index.m3u8$zuidam3u8#第10集$http://mojing.huoyanzuida.com/20200428/2837_cadf73b2/index.m3u8$zuidam3u8#第11集$http://mojing.huoyanzuida.com/20200428/2843_c117b39b/index.m3u8$zuidam3u8#第12集$http://mojing.huoyanzuida.com/20200428/2839_501c9d7e/index.m3u8$zuidam3u8#第13集$http://mojing.huoyanzuida.com/20200428/2841_7c5648a8/index.m3u8$zuidam3u8#第14集$http://mojing.huoyanzuida.com/20200428/2842_d9cc1dbd/index.m3u8$zuidam3u8#第15集$http://mojing.huoyanzuida.com/20200428/2846_f61cb2d6/index.m3u8$zuidam3u8#第16集$http://mojing.huoyanzuida.com/20200428/2844_6bc4d8b5/index.m3u8$zuidam3u8#第17集$http://mojing.huoyanzuida.com/20200428/2845_4cddf48c/index.m3u8$zuidam3u8#第18集$http://mojing.huoyanzuida.com/20200428/2847_5814d84b/index.m3u8$zuidam3u8#第19集$http://mojing.huoyanzuida.com/20200428/2848_95701311/index.m3u8$zuidam3u8#第20集$http://mojing.huoyanzuida.com/20200428/2849_0b7b651b/index.m3u8$zuidam3u8#第21集$http://mojing.huoyanzuida.com/20200428/2850_96e088f9/index.m3u8$zuidam3u8#第22集$http://mojing.huoyanzuida.com/20200428/2851_aa476aa4/index.m3u8$zuidam3u8"}}, "des": "宝（李克勤 饰）一直生活于庙街，小时候因为与母亲失散了而被老江湖杨合益收养了。一直受青梅竹马的何喜（叶璇 饰）照顾，两人感情就像兄妹。 一名家庭主妇英（黄淑仪 饰）突然出现在了宝的生活中，并坚称宝就是她当年失散的儿子，令无拘无束的宝不胜其烦。同时英做警察的儿子王文迪（梁汉文 饰）对阿宝十分反感，更因为误会与阿宝成为敌人。这时令宝更加不能接受的是，何喜一直暗恋文迪，宝只好黯然退出。 宝对英的态度虽然比以前缓和了，但英见两名儿子互相争斗，仍十分痛心。这时庙街里有权力之人在作威作福，宝决定带领自己的一众好友与文迪共同与恶势力抗争。"}, {"last": "2020-04-29 00:36:20", "id": "84711", "tid": "13", "name": "金牙大状2粤语", "type": "香港剧", "pic": "https://tu.tianzuida.com/pic/upload/vod/2020-04-29/202004291588091761.jpg", "lang": "粤语", "area": "香港", "year": "1995", "state": "0", "note": "20集全", "actor": "郑丹瑞,伍咏薇,何宝生,梁艺龄,崔嘉宝,黄一飞,张国强,关海山,黎汉持", "director": null, "dl": {"dd": {"@flag": "zuidam3u8", "#text": "第01集$http://mojing.huoyanzuida.com/20200428/2772_73c21107/index.m3u8$zuidam3u8#第02集$http://mojing.huoyanzuida.com/20200428/2776_718046e9/index.m3u8$zuidam3u8#第03集$http://mojing.huoyanzuida.com/20200428/2773_48323485/index.m3u8$zuidam3u8#第04集$http://mojing.huoyanzuida.com/20200428/2774_853e0756/index.m3u8$zuidam3u8#第05集$http://mojing.huoyanzuida.com/20200428/2775_3f512cba/index.m3u8$zuidam3u8#第06集$http://mojing.huoyanzuida.com/20200428/2779_aeea9a1f/index.m3u8$zuidam3u8#第07集$http://mojing.huoyanzuida.com/20200428/2777_4c610c1e/index.m3u8$zuidam3u8#第08集$http://mojing.huoyanzuida.com/20200428/2778_5a822c03/index.m3u8$zuidam3u8#第09集$http://mojing.huoyanzuida.com/20200428/2780_ebff8dbd/index.m3u8$zuidam3u8#第10集$http://mojing.huoyanzuida.com/20200428/2781_309dc845/index.m3u8$zuidam3u8#第11集$http://mojing.huoyanzuida.com/20200428/2782_89f2e141/index.m3u8$zuidam3u8#第12集$http://mojing.huoyanzuida.com/20200428/2783_44f13e2f/index.m3u8$zuidam3u8#第13集$http://mojing.huoyanzuida.com/20200428/2784_e6772370/index.m3u8$zuidam3u8#第14集$http://mojing.huoyanzuida.com/20200428/2785_41085d9c/index.m3u8$zuidam3u8#第15集$http://mojing.huoyanzuida.com/20200428/2786_77e52ca3/index.m3u8$zuidam3u8#第16集$http://mojing.huoyanzuida.com/20200428/2787_bcc88354/index.m3u8$zuidam3u8#第17集$http://mojing.huoyanzuida.com/20200428/2789_e94ed26b/index.m3u8$zuidam3u8#第18集$http://mojing.huoyanzuida.com/20200428/2788_bbe3597f/index.m3u8$zuidam3u8#第19集$http://mojing.huoyanzuida.com/20200428/2790_8fc3df9e/index.m3u8$zuidam3u8#第20集$http://mojing.huoyanzuida.com/20200428/2792_a4bbe233/index.m3u8$zuidam3u8#第21集$http://mojing.huoyanzuida.com/20200428/2791_419d8281/index.m3u8$zuidam3u8#第22集$http://mojing.huoyanzuida.com/20200428/2793_b2c11021/index.m3u8$zuidam3u8#第23集$http://mojing.huoyanzuida.com/20200428/2794_0fb6ad4b/index.m3u8$zuidam3u8#第24集$http://mojing.huoyanzuida.com/20200428/2795_ffb9e9a8/index.m3u8$zuidam3u8#第25集$http://mojing.huoyanzuida.com/20200428/2796_ae870184/index.m3u8$zuidam3u8#第26集$http://mojing.huoyanzuida.com/20200428/2797_f90557ac/index.m3u8$zuidam3u8#第27集$http://mojing.huoyanzuida.com/20200428/2798_9b82313b/index.m3u8$zuidam3u8#第28集$http://mojing.huoyanzuida.com/20200428/2799_904e18af/index.m3u8$zuidam3u8#第29集$http://mojing.huoyanzuida.com/20200428/2800_eae9f560/index.m3u8$zuidam3u8#第30集$http://mojing.huoyanzuida.com/20200428/2801_8a0d46d9/index.m3u8$zuidam3u8#第31集$http://mojing.huoyanzuida.com/20200428/2802_8565b75e/index.m3u8$zuidam3u8#第32集$http://mojing.huoyanzuida.com/20200428/2803_d6fc919e/index.m3u8$zuidam3u8#第33集$http://mojing.huoyanzuida.com/20200428/2804_8682f6e4/index.m3u8$zuidam3u8#第34集$http://mojing.huoyanzuida.com/20200428/2805_959e4a34/index.m3u8$zuidam3u8#第35集$http://mojing.huoyanzuida.com/20200428/2806_d102957c/index.m3u8$zuidam3u8#第36集$http://mojing.huoyanzuida.com/20200428/2807_0fcb4459/index.m3u8$zuidam3u8#第37集$http://mojing.huoyanzuida.com/20200428/2808_310907a0/index.m3u8$zuidam3u8#第38集$http://mojing.huoyanzuida.com/20200428/2809_498fc171/index.m3u8$zuidam3u8#第39集$http://mojing.huoyanzuida.com/20200428/2810_6c7d7cfd/index.m3u8$zuidam3u8#第40集$http://mojing.huoyanzuida.com/20200428/2811_77486ef0/index.m3u8$zuidam3u8"}}, "des": "戴亚斗（郑丹瑞）获慈禧御赐金牙，成为金牙大状，为人排难申冤名满全城，斗在诉讼的过程中，不但伸张正义，而且更能指出法理与人情之精结所在，每每令人拍案叫绝，身边还有个精通医术的得力助手袁灵芝（梁佩玲）。 王日出（何宝生）无辜被卷入名妓施思（郭少芸）的谋杀案中，斗为出澄清白，代他提出诉讼，并遇上北铁嘴田一农（张国强），两人展开激烈对辩。斗找出罪证力指此案与新任巡抚有关，怎料最后却被揭发思纯为自杀而死。斗虽败诉，但在过程中滔滔雄辩大义凛然，终于感动出愿意追随他作入室弟子。 斗往赴陈梦吉（关海山）之封笔大会，却在大典上遇唐冠石（伍咏薇）。吉被石诬陷入狱，斗为救吉与石对抗，除揭穿石乃女子之身，并发现其为方唐镜之女方田影，两人遂成为斗气冤家。 尔后，在一宗英人强奸中国村妇案件中，斗与影各自代表中、英双方，互在公堂上对辩，两人更展开一场激烈对辩……"}, {"last": "2020-04-29 07:40:34", "id": "84712", "tid": "17", "name": "天真浪漫伊贺真子", "type": "伦理片", "pic": "https://tu.tianzuida.com/pic/upload/vod/2020-04-29/202004291588117196.jpg", "lang": "日语", "area": "日本", "year": "2020", "state": "0", "note": "BD高清", "actor": "伊賀まこ", "director": null, "dl": {"dd": {"@flag": "zuidam3u8", "#text": "BD高清$https://yiqikan.wuyouzuida.com/20200428/4537_a7ec53ee/index.m3u8$zuidam3u8"}}, "des": "天真浪漫！雷吉突发！3月最强的美少女伊贺真子袭击了！好久没看到这么可怕的新人了！<br />她的名字是“「伊贺まこ(伊贺真子)」”，是3月19日发售的邪恶帝国S 1的新人。因为这部作品被搁置了下来，所以不是在销售排行榜第一、第二位，而是在讨论区获得了日本的粉丝。全会一致称赞…<br />但是，坦率地说，这是我认为最难判断的女演员。没想到，据说我被蛇咬了10年，害怕草绳。初期少女路易（初期少女路易）的照片会很悲惨吧。滑铁卢对于中国台湾粉丝感到吃惊的日本美女的接受度似乎不高或中等。我来类推一下。最近自己爆发性的家政非常严格，结婚前的做爱被严格禁止，但是为了拍AV而跑的户田真琴在日本很红吗？但是，如果你想让她来台湾照相的话，我会反复考虑，我不会下决定的…但是，那没关系，我还没有时间考虑这个新人是否会受到中国粉丝的欢迎，PoiT成为了伊贺真子（伊贺真子）日本粉丝最期待的女演员<br />因为她非常温柔可爱，所以回答很简单！"}, {"last": "2020-04-29 07:43:38", "id": "84713", "tid": "17", "name": "她爱你　保田真愛", "type": "伦理片", "pic": "https://tu.tianzuida.com/pic/upload/vod/2020-04-29/202004291588117385.jpg", "lang": "日语", "area": "日本", "year": "2020", "state": "0", "note": "BD高清", "actor": "保田真愛", "director": null, "dl": {"dd": {"@flag": "zuidam3u8", "#text": "BD高清$https://yiqikan.wuyouzuida.com/20200428/4536_6be85d02/index.m3u8$zuidam3u8"}}, "des": "流行的魅力模特偶像[Maai Yasuda]的最新DVD将以短版剪裁和可爱的面孔发行！!!她的身材苗条，有可爱的布丁臀部。 在每种情况下，您都可以享受性感成人的性感[Maai Yasuda]除了粉丝，这是必看的杰作！"}, {"last": "2020-04-29 07:47:02", "id": "84714", "tid": "17", "name": "美少女城秘密纪念馆", "type": "伦理片", "pic": "https://tu.tianzuida.com/pic/upload/vod/2020-04-29/202004291588117592.jpg", "lang": "日语", "area": "日本", "year": "2020", "state": "0", "note": "BD高清", "actor": "桃井あやか･平野もえ", "director": null, "dl": {"dd": {"@flag": "zuidam3u8", "#text": "BD高清$https://yiqikan.wuyouzuida.com/20200428/4535_7bb2a818/index.m3u8$zuidam3u8"}}, "des": "这是预约商品。完美身材的【桃井あかか】和白桃天使【平野もえ】的共同演出DVD登场了在肌肤上打磨过的萌酱白光般光滑的肌肤，滋润着润润感；在沙滩上打闹，“对彼此都是秘密”心跳的时间也……虽然脸很可爱，但是身体已经成熟了，你能忍受两个人的身体吗？"}, {"last": "2020-04-29 07:49:42", "id": "84715", "tid": "17", "name": "美少女伝説　蜜之旅", "type": "伦理片", "pic": "https://tu.tianzuida.com/pic/upload/vod/2020-04-29/202004291588117756.jpg", "lang": "日语", "area": "日本", "year": "2020", "state": "0", "note": "BD高清", "actor": "椎野うい・平野もえ", "director": null, "dl": {"dd": {"@flag": "zuidam3u8", "#text": "BD高清$https://yiqikan.wuyouzuida.com/20200428/4534_bb3f20d7/index.m3u8$zuidam3u8"}}, "des": "有着能让人露出蓝色肌肤的白色的两人【椎名姐姐】&amp;【平野もえ】的共演印象作品登场了从以前开始就很熟悉的怀才子和其他学校的学生一起进行的魅惑的【もえ】好好地限定3天的联合集训！在院子里洒水玩，穿紧身衣做伸展运动，在房间里按摩疲惫的身体，穿学校泳衣做准备体操的话，场景和来自那里的妄想就会膨胀…在这之中展开的甜蜜恋爱的三角关系是怎样的？"}, {"last": "2020-04-29 07:51:55", "id": "84716", "tid": "17", "name": "美少女伝説　白桃天使　平野もえ", "type": "伦理片", "pic": "https://tu.tianzuida.com/pic/upload/vod/2020-04-29/202004291588117888.jpg", "lang": "日语", "area": "日本", "year": "2020", "state": "0", "note": "BD高清", "actor": "白桃天使　平野もえ", "director": null, "dl": {"dd": {"@flag": "zuidam3u8", "#text": "BD高清$https://yiqikan.wuyouzuida.com/20200428/4533_b44cf668/index.m3u8$zuidam3u8"}}, "des": "像棉花糖一样粘糯的白桃天使【平野もえ】最新DVD在沙滩上萌酱可以涂防晒霜，用平衡球滚动身体，在网球上一起流汗，和萌酱一起度过时光。包裹着我的身体，在床上温柔地微笑着……收录了只有你才知道的萌酱可爱的样子，也扮演了弗里弗里的可爱女佣♪天真无邪全力投球的萌酱无法移开视线"}, {"last": "2020-04-29 07:54:03", "id": "84717", "tid": "17", "name": "恋爱糸狂想曲", "type": "伦理片", "pic": "https://tu.tianzuida.com/pic/upload/vod/2020-04-29/202004291588117993.jpg", "lang": "日语", "area": "日本", "year": "2020", "state": "0", "note": "BD高清", "actor": "井上灯香里", "director": null, "dl": {"dd": {"@flag": "zuidam3u8", "#text": "BD高清$https://yiqikan.wuyouzuida.com/20200428/4532_98af1a5f/index.m3u8$zuidam3u8"}}, "des": "天真无邪的笑容让人怦然心动的清纯美少女“井上灯香里”，总之一边害羞一边挑战初次体验的写真集，像十几岁的女孩子一样，在普通人理所当然的害羞场面上连呼“好害羞”的天真可爱。柔软的皮肤也很耀眼，还残留着稚嫩部分的10代特有的不成熟的全部和“这样的孩子……”“”和意外的曝光和意外事件，把它塞进了这部作品里。请享受一下清新的美少女挑战大胆的姿势和演出的“大胆的反差”吧！"}, {"last": "2020-04-29 07:58:00", "id": "84718", "tid": "17", "name": "红辣椒", "type": "伦理片", "pic": "https://tu.tianzuida.com/pic/upload/vod/2020-04-29/202004291588118228.jpg", "lang": "英语", "area": "美国", "year": "1991", "state": "0", "note": "HD高清", "actor": "Debora Caprioglio, Stéphane Ferrara, Martine Brochard", "director": "Tinto Brass", "dl": {"dd": {"@flag": "zuidam3u8", "#text": "HD高清$https://yiqikan.wuyouzuida.com/20200428/4531_810f2fed/index.m3u8$zuidam3u8"}}, "des": "1950年代，意大利在妓院禁令即将来临之前，一个没有经验的乡村姑娘Mimma勉强接受了妓女的工作。 而且，就这样，这个曾经纯真的女人成为了辣椒粉，寄希望于筹集足够的钱来为她的无用男朋友提供资金。 不久之后，辣椒粉将学会享受她那声名狼藉但仍然非常有利可图的职业，在繁华的罗马市从一个妓院到另一个妓院旅行的过程中，一次一次地提升自己的客户。 然而，尽管辣椒粉进行了自我发现，经验和性解放的风雨如磐的繁荣之旅，但在她貌似充实的生活中仍然缺少一件事：发掘真爱的巨大奥秘。 辣椒粉是要体验激情的浪漫吗？"}, {"last": "2020-04-29 08:01:12", "id": "84719", "tid": "17", "name": "十字架  前編", "type": "伦理片", "pic": "https://tu.tianzuida.com/pic/upload/vod/2020-04-29/202004291588118442.jpg", "lang": "日语", "area": "日本", "year": "2020", "state": "0", "note": "HD高清", "actor": "内详", "director": null, "dl": {"dd": {"@flag": "zuidam3u8", "#text": "HD高清$https://yiqikan.wuyouzuida.com/20200428/4530_7a6464f5/index.m3u8$zuidam3u8"}}, "des": "[Queen Bee]上篇[女王蜂] Harusuke第1部分[Queen Bee]十字架前篇"}, {"last": "2020-04-29 08:03:03", "id": "84720", "tid": "17", "name": "李小龙与我", "type": "伦理片", "pic": "https://tu.tianzuida.com/pic/upload/vod/2020-04-29/202004291588118520.jpg", "lang": "国语", "area": "香港", "year": "1976", "state": "0", "note": "HD高清中文字幕", "actor": "李修贤,丁佩,王沙", "director": "罗马", "dl": {"dd": {"@flag": "zuidam3u8", "#text": "HD高清$https://yiqikan.wuyouzuida.com/20200428/4529_949d89b8/index.m3u8$zuidam3u8"}}, "des": "丁佩以自己的角度，把功夫影帝李小龙生前一切的第一手事实，毫无保留地公诸于世，包括她如何认识李小龙，及重逢後如何发展成可以倾诉肺腑之言的红颜知己。究竟李小龙与丁佩在私生活中，是缠绵的爱情、抑或纯洁的友谊，在银幕上自有说明。而全片最珍贵的部分，当然是对李小龙死因的交代。 本片应是李小龙死後第一部描述其生前事迹的电影，主要描述了他与情人丁佩的最後时光，因为一代大侠李小龙于1973年7月20日晚间就死于丁佩的闺房。影片拍摄于1975年，由执导过《出笼马骝》的武侠片导演罗马执导，李修贤饰演李小龙，由唯一知道李小龙死因的密友丁佩提供剧本，兼亲身饰演自己。一直以来，李小龙的死因都是疑点重重，因为人们普遍认为像李小龙这种身体状况极佳的年轻人，怎麽会在一夜之间死去呢？ 想当年李小龙回港大展鸿图之时，丁佩也正在香港演艺圈寻求发展，二人可谓一见锺情。丁佩在美女如云的演艺圈虽然不显美艳惊人，但她豪爽的性情、妩媚的体态却正投李小龙所好，交往後二人几乎形影不离，成为李小龙众多绯闻女友中媒介所认为的惟一「证据确凿」的情人。本片就是当年了解李小龙死因的「新闻人物」丁佩，以自己的角度出发，讲述了她与李小龙从相识相恋，到不幸发生的过程，自然透露出一些鲜为人知的「真相」。但所谓「当局者迷」，这种男女感情之事由当事者本人去叙述是很难说明白的，里面不免会掺杂着个人的情感恩怨因素。不过观众可以从另一个角度来领略一下李小龙的情感世界，可谓「仁者见仁，智者见智」，这也是本片的价值所在。尽管一代武术宗师身上发生的风流韵事令人难于接受，但这也无损李小龙为弘扬中华武术所作出的卓越贡献。 丁珮的肉弹形象一览无余,可惜露点床戏用了替身,但身材与她超象,片子是丁珮影片与SB合作的,为她自己解释很多,毕竟当时李才刚去世两年,压力不小,丁珮影片公司的英文名是B &amp; B,应该是二人英文名Betty &amp; Bruce.徐小凤出场两次,身份是酒吧驻唱歌手,都是唱那首名曲&quot;长发为君剪&quot;,长发为君剪,短发为君留,发型永不变,以示常相守......嘉禾几位大佬,邹文怀,罗维,何冠昌都尽量做到形似,只是邹文怀被改名为孔明.制片陆小姐我猜是指罗维妻子刘亮华.另外两个露点的无名女,第2个比较好看. 李小龍死後，此應為第一部描述其生前事跡的電影，拍攝於1975年，羅馬導演，李修賢飾李小龍，並由唯一知道李氏死因的密友丁珮提供劇本，兼親身飾演自己。在片中丁珮以自己的角度，把一切第一手事實，毫無保留地公諸於世，包括丁如何認識李氏，及重逢後如何發展成可以傾訴肺腑之言的知己。究竟李與丁在私生活中，是纏綿的愛情、抑或純潔的友誼，在銀幕上自有說明。而全片最珍貴的部分，當然是對李氏死因的交代。"}, {"last": "2020-04-29 08:07:12", "id": "84721", "tid": "17", "name": "禁忌4年轻一代", "type": "伦理片", "pic": "https://tu.tianzuida.com/pic/upload/vod/2020-04-29/202004291588118786.jpg", "lang": "英语", "area": "美国", "year": "1985", "state": "0", "note": "HD高清", "actor": "史蒂夫·海特纳,Susan Block,杰瑞·巴特勒", "director": "Kirdy Stevens", "dl": {"dd": {"@flag": "zuidam3u8", "#text": "HD高清$https://yiqikan.wuyouzuida.com/20200428/4528_54df8813/index.m3u8$zuidam3u8"}}, "des": "害羞的女孩与她的妹妹在严格的寄宿学校同住一个房间。 在姐姐的建议下，她与男友发生性关系，两个女孩被开除出该机构。 他们的精神科医生父亲发现他的妻子与姐夫有外遇，后者后来与侄女发生了性关系。"}, {"last": "2020-04-29 08:12:49", "id": "84722", "tid": "17", "name": "性世界", "type": "伦理片", "pic": "https://tu.tianzuida.com/pic/upload/vod/2020-04-29/202004291588119074.jpg", "lang": "英语", "area": "美国", "year": "1978", "state": "0", "note": "HD高清", "actor": "Dominique Alavoine / Richard Allan / Christina Anders / Nelly Bergman / Catring", "director": "Andrei Feher", "dl": {"dd": {"@flag": "zuidam3u8", "#text": "HD高清$https://yiqikan.wuyouzuida.com/20200428/4527_5f5ce70e/index.m3u8$zuidam3u8"}}, "des": "国家：瑞典<br />语言：瑞典语<br />发行日期：1985年3月4日（瑞典）查看更多»<br />也称为：Les stoppeuses ne portent pas de culottes查看更多»"}, {"last": "2020-04-29 08:16:17", "id": "84723", "tid": "17", "name": "裸神相泽南", "type": "伦理片", "pic": "https://tu.tianzuida.com/pic/upload/vod/2020-04-29/202004291588119300.jpg", "lang": "日语", "area": "日本", "year": "2020", "state": "0", "note": "BD高清", "actor": "相沢みなみ", "director": null, "dl": {"dd": {"@flag": "zuidam3u8", "#text": "BD高清$https://yiqikan.wuyouzuida.com/20200428/4526_f105e48c/index.m3u8$zuidam3u8"}}, "des": "大家还记得首次看到相泽南（相沢みなみ）的时候是什么样的吗？这个问题是她在今天台湾拍摄的时候问当场粉丝们的问题，但是看到粉丝们的回答，好像不是那么多人知道，因为许多人是在最近的时间里才成为她的粉丝的，其实相泽南（相沢みなみ）的外貌还是比较出众的。接下来请问大家对相泽南的作品说出最喜欢的是哪个，在拍摄的过程中说的最多的也就是她的作品了，这部作品也算是她最好的作品了，无论是表情还是演技还是心里变化都是最好的，也算是近来最经典的作品了，也不知道她对自己最满意的作品会是哪个呢，一定是。她也算是很适合这样的作品了，在出演的时候她的穿的是女仆的衣服，也是对她进行的，在剧情中的表现还是很让人难忘的，这样的作品还是很让相泽南记忆深刻的，因为其中有一段的剧情是她在受不了的情况下当记者访问到她的在剧情中表演的怎么样，她却说“其实也就和正常人的皮肤没啥区别啦，但是有些地方的毛孔里面掺杂着细细的毛毛让人感到不一样”。"}, {"last": "2020-04-29 08:21:09", "id": "84724", "tid": "17", "name": "SPY Film间谍电影", "type": "伦理片", "pic": "https://tu.tianzuida.com/pic/upload/vod/2020-04-29/202004291588119550.jpg", "lang": "日语", "area": "日本", "year": "2020", "state": "0", "note": "BD高清", "actor": "水トさくら", "director": null, "dl": {"dd": {"@flag": "zuidam3u8", "#text": "BD高清$https://yiqikan.wuyouzuida.com/20200428/4525_0ebbc964/index.m3u8$zuidam3u8"}}, "des": "水卜樱，（水卜さくら，Miura Sakura），1997年出生于日本，水卜樱可以算5月最重要的新人之一，而她的出道不但可以解释为什么另一位身材教科书桜空もも(樱空桃)会去了ideapocket发片。还被称为“10年才有一个的神乳”，女优长相不算太漂亮，但是青春可爱，看着还是挺符合萝莉的主题。姓 名：水卜樱<br />别 名：水卜さくら（Miura Sakura）<br />国 籍：日本<br />出道时间：2017年5月<br />年 龄：1997年11月30日<br />身 高：152cm<br />三 围：B79 W52 H78 cm"}, {"last": "2020-04-29 08:22:56", "id": "84725", "tid": "17", "name": "恋爱刺客", "type": "伦理片", "pic": "https://tu.tianzuida.com/pic/upload/vod/2020-04-29/202004291588119743.jpg", "lang": "英语", "area": "美国", "year": "2006", "state": "0", "note": "HD高清", "actor": "杰西·麦特卡尔菲,布兰特妮·斯诺,亚香缇,索菲亚·布什,佩恩·拜德格雷,詹尼·麦卡锡,阿莉尔·凯贝尔", "director": "贝蒂·托马斯", "dl": {"dd": {"@flag": "zuidam3u8", "#text": "HD高清$https://yiqikan.wuyouzuida.com/20200428/4524_ab5b13ca/index.m3u8$zuidam3u8"}}, "des": "约翰•塔克（杰西•麦特卡尔菲 饰）是学校里面的风头人物，深受女孩子的欢迎，他也乐在其中。不久，他的三位美丽的女友嘉丽、希瑟、贝丝发现了自己的男友都是约翰。感到晴天霹雳的三人决定一争到底，但最后都躲不过被约翰抛弃的命运。 本是敌人的她们伤心过后决定联合起来一起对付约翰，惩罚他的花心之举。可是她们的计划在约翰身上并不奏效。这时善良单纯的凯特（布兰特妮•斯诺 饰）成为了她们报复约翰的工具，凯特虽然心里不太愿意，因为她需要诱惑约翰，之后再让他品尝失恋之苦。可是她也希望能走进三位校花的生活圈子中，便同意了。果然，约翰对打扮后美得不可方物的凯特动心不已，竟变了个人似的对凯特的感情专一认真。凯特本来想自己的任务即将完成，可是却发现自己真的爱上了约翰……"}, {"last": "2020-04-29 08:25:26", "id": "84726", "tid": "17", "name": "激情家族", "type": "伦理片", "pic": "https://tu.tianzuida.com/pic/upload/vod/2020-04-29/202004291588119894.jpg", "lang": "其它", "area": "美国", "year": "1995", "state": "0", "note": "HD高清", "actor": "Shauna O'Brien,Griffin Drew,Burke Morgan,Lisa Boyle,Will Potter,Raelyn Saalman,Alex Demir", "director": "Edward Holzman", "dl": {"dd": {"@flag": "zuidam3u8", "#text": "HD高清$https://yiqikan.wuyouzuida.com/20200428/4523_92693b74/index.m3u8$zuidam3u8"}}, "des": "一位神秘的流浪者在偶然的情况下试图唤醒某富有但性冷淡家族的故事，他和她之间有浪漫的爱情也有不为人知的秘密。卡罗维发利"}, {"last": "2020-04-29 08:27:29", "id": "84727", "tid": "17", "name": "野蛮女王2-女王的反击", "type": "伦理片", "pic": "https://tu.tianzuida.com/pic/upload/vod/2020-04-29/202004291588119998.jpg", "lang": "英语", "area": "美国", "year": "1992", "state": "0", "note": "HD高清", "actor": "拉娜·克拉克森,格雷格·瓦格内尔", "director": "Joe Finley", "dl": {"dd": {"@flag": "zuidam3u8", "#text": "HD高清$https://yiqikan.wuyouzuida.com/20200428/4522_8ddef650/index.m3u8$zuidam3u8"}}, "des": "在《野蛮女王》（Barbarian Queen）（1985）中击败了邪恶的阿拉库尔勋爵（Lord Arrakur）之后，无所畏惧的野蛮战士阿萨莉亚公主（Princess Athalia）和她的人民发现自己受到了另一种邪恶的狂妄自大的控制：渴望权力的Ankaris。当这位野心勃勃的君主竭尽所能地利用前国王魔法权杖的神力时，阿萨莉亚必须在不可侵犯的城堡阴暗潮湿的地牢里忍受无尽的折磨，才能与凶猛的战友团聚。现在，冷冰冰、赤裸裸的钢铁有了最后的发言权。谁敢挑战王国的合法继承人，凶残的野蛮女王？"}, {"last": "2020-09-02 09:39:06", "id": "84728", "tid": "4", "name": "恋上原来的我", "type": "动漫片", "pic": "https://tu.tianzuida.com/pic/upload/vod/2020-04-29/202004291588123497.jpg", "lang": "国语", "area": "大陆", "year": "2020", "state": "0", "note": "更新到19集", "actor": "内详", "director": "未知", "dl": {"dd": {"@flag": "zuidam3u8", "#text": "第01集$http://douban.donghongzuida.com/20200429/1271_238ffcf8/index.m3u8$zuidam3u8#第02集$http://douban.donghongzuida.com/20200429/1273_8596e67e/index.m3u8$zuidam3u8#第03集$http://douban.donghongzuida.com/20200429/1272_1a750b12/index.m3u8$zuidam3u8#第04集$http://douban.donghongzuida.com/20200520/2368_69c92626/index.m3u8$zuidam3u8#第05集$http://douban.donghongzuida.com/20200527/2622_3766eba7/index.m3u8$zuidam3u8#第06集$http://douban.donghongzuida.com/20200603/3003_655b849f/index.m3u8$zuidam3u8#第07集$http://douban.donghongzuida.com/20200610/3408_11cf49e0/index.m3u8$zuidam3u8#第08集$http://yuledy.helanzuida.com/20200616/6024_3008b2fb/index.m3u8$zuidam3u8#第09集$http://xigua-cdn.haima-zuida.com/20200623/8502_c0340c3e/index.m3u8$zuidam3u8#第10集$http://douban.donghongzuida.com/20200701/4644_9a41d8cb/index.m3u8$zuidam3u8#第11集$http://douban.donghongzuida.com/20200708/5021_bf34bf01/index.m3u8$zuidam3u8#第12集$http://douban.donghongzuida.com/20200715/5525_f8af444e/index.m3u8$zuidam3u8#第13集$http://douban.donghongzuida.com/20200728/6293_87f4c48e/index.m3u8$zuidam3u8#第14集$http://xigua-cdn.haima-zuida.com/20200728/9569_99201714/index.m3u8$zuidam3u8#第15集$http://douban.donghongzuida.com/20200805/6775_f1a196b0/index.m3u8$zuidam3u8#第16集$http://douban.donghongzuida.com/20200812/7180_a506609a/index.m3u8$zuidam3u8#第17集$http://yuledy.helanzuida.com/20200818/9140_1075de4c/index.m3u8$zuidam3u8#第18集$http://douban.donghongzuida.com/20200826/8248_c87f2aa7/index.m3u8$zuidam3u8#第19集$http://douban.donghongzuida.com/20200902/8789_efafa156/index.m3u8$zuidam3u8"}}, "des": "顾云在一场车祸后穿越回10年前，成为唐家二小姐唐凌曦。重活一世，她凭着前世的见识与谋略成为了唐家家主，并在这一路上，不经意间收获了一份真挚的爱情。"}, {"last": "2020-07-29 13:50:41", "id": "84729", "tid": "4", "name": "隐世华族", "type": "动漫片", "pic": "https://tu.tianzuida.com/pic/upload/vod/2020-04-29/202004291588125364.jpg", "lang": "国语", "area": "大陆", "year": "2020", "state": "0", "note": "更新到15集", "actor": "内详", "director": "未知", "dl": {"dd": {"@flag": "zuidam3u8", "#text": "第01集$http://yuledy.helanzuida.com/20200428/3206_e2863c6e/index.m3u8$zuidam3u8#第02集$http://yuledy.helanzuida.com/20200428/3205_5e244036/index.m3u8$zuidam3u8#第03集$http://xigua-cdn.haima-zuida.com/20200505/6801_290aa3b7/index.m3u8$zuidam3u8#第04集$http://yuledy.helanzuida.com/20200512/4006_1ed299c1/index.m3u8$zuidam3u8#第05集$http://xigua-cdn.haima-zuida.com/20200519/7340_0aaa4d89/index.m3u8$zuidam3u8#第06集$http://douban.donghongzuida.com/20200527/2626_c14ae135/index.m3u8$zuidam3u8#第07集$http://douban.donghongzuida.com/20200603/3006_1b50d6cb/index.m3u8$zuidam3u8#第08集$http://yuledy.helanzuida.com/20200609/5631_140a999e/index.m3u8$zuidam3u8#第09集$http://xigua-cdn.haima-zuida.com/20200616/8154_0adbd10d/index.m3u8$zuidam3u8#第10集$http://yuledy.helanzuida.com/20200623/6361_8a5ca679/index.m3u8$zuidam3u8#第11集$http://douban.donghongzuida.com/20200701/4660_1a4fd759/index.m3u8$zuidam3u8#第12集$http://douban.donghongzuida.com/20200708/5031_8315cbd9/index.m3u8$zuidam3u8#第13集$http://xigua-cdn.haima-zuida.com/20200714/9184_f03df316/index.m3u8$zuidam3u8#第14集$http://xigua-cdn.haima-zuida.com/20200721/9336_77dd4462/index.m3u8$zuidam3u8#第15集$http://douban.donghongzuida.com/20200729/6335_d3bf53bf/index.m3u8$zuidam3u8"}}, "des": "大学女生白墨桃在课外活动中于雷峰塔误入豪门公子尹苍冬的结界，而尹苍冬实际身份却是隐藏于人类世界的神羽族继承人，尹苍冬认定白墨桃是宿敌蛇族一员，对白墨桃展开..."}, {"last": "2020-04-30 16:39:28", "id": "84730", "tid": "12", "name": "七黄五狼黑之神机秘策", "type": "国产剧", "pic": "https://tu.tianzuida.com/pic/upload/vod/2020-04-29/202004291588125604.jpg", "lang": "国语", "area": "大陆", "year": "2017", "state": "0", "note": "10集全", "actor": "孙博文,孙亚龙,李浩宇,拳师七号,周淑怡,刘秋实,张晓唯", "director": "刘坦", "dl": {"dd": {"@flag": "zuidam3u8", "#text": "第01集$http://shishang.dingxiangzuida.com/20200429/626_54c6d443/index.m3u8$zuidam3u8#第02集$http://shishang.dingxiangzuida.com/20200429/625_9d33faca/index.m3u8$zuidam3u8#第03集$http://shishang.dingxiangzuida.com/20200429/624_138e8f68/index.m3u8$zuidam3u8#第04集$http://shishang.dingxiangzuida.com/20200429/623_489ee316/index.m3u8$zuidam3u8#第05集$http://shishang.dingxiangzuida.com/20200429/622_f0413845/index.m3u8$zuidam3u8#第06集$http://shishang.dingxiangzuida.com/20200429/621_f5d81db0/index.m3u8$zuidam3u8#第07集$http://shishang.dingxiangzuida.com/20200429/619_eae86f4e/index.m3u8$zuidam3u8#第08集$http://shishang.dingxiangzuida.com/20200429/620_7d8865ba/index.m3u8$zuidam3u8#第09集$http://shishang.dingxiangzuida.com/20200429/618_e490e722/index.m3u8$zuidam3u8#第10集$http://shishang.dingxiangzuida.com/20200429/617_1001df93/index.m3u8$zuidam3u8"}}, "des": "这是一部网络古装轻喜剧，讲述的是七剑宗庄主孙景麒、与不空、九号、西门、飞花等众人意外卷入一场武林纷争，随即开启的一场哭笑不得的江湖之旅。"}, {"last": "2020-04-30 16:39:17", "id": "84731", "tid": "12", "name": "囧西游2： 蜜汁大魔王", "type": "国产剧", "pic": "https://tu.tianzuida.com/pic/upload/vod/2020-04-29/202004291588125694.jpg", "lang": "国语", "area": "大陆", "year": "2016", "state": "0", "note": "11集全", "actor": "代文雯,高正,李易霖", "director": "牛毛毛", "dl": {"dd": {"@flag": "zuidam3u8", "#text": "第01集$http://shishang.dingxiangzuida.com/20200429/647_2fb0fc0b/index.m3u8$zuidam3u8#第02集$http://shishang.dingxiangzuida.com/20200429/646_adca2ad2/index.m3u8$zuidam3u8#第03集$http://shishang.dingxiangzuida.com/20200429/645_df87cab8/index.m3u8$zuidam3u8#第04集$http://shishang.dingxiangzuida.com/20200429/644_8d26d06c/index.m3u8$zuidam3u8#第05集$http://shishang.dingxiangzuida.com/20200429/643_6fc54f4b/index.m3u8$zuidam3u8#第06集$http://shishang.dingxiangzuida.com/20200429/642_0026c2f8/index.m3u8$zuidam3u8#第07集$http://shishang.dingxiangzuida.com/20200429/641_5fb31a88/index.m3u8$zuidam3u8#第08集$http://shishang.dingxiangzuida.com/20200429/640_3ab0caa2/index.m3u8$zuidam3u8#第09集$http://shishang.dingxiangzuida.com/20200429/639_244a8f5a/index.m3u8$zuidam3u8#第10集$http://shishang.dingxiangzuida.com/20200429/637_00e64108/index.m3u8$zuidam3u8#第11集$http://shishang.dingxiangzuida.com/20200429/638_7961b6f2/index.m3u8$zuidam3u8"}}, "des": "唐僧师徒西行取经，因选错对手经验值被杀得片甲不留、瞬间损失75%的兵力。如来心生慈悲，搬来援兵支持，于是在美美哒小白龙陪伴下，此行道路万里艰险，倒也因为一路囧事不断、离奇不止，令取经路充满了意外与乐趣。"}, {"last": "2020-04-30 16:39:03", "id": "84732", "tid": "12", "name": "花飞尽、归不归", "type": "国产剧", "pic": "https://tu.tianzuida.com/pic/upload/vod/2020-04-29/202004291588125817.jpg", "lang": "国语", "area": "大陆", "year": "2016", "state": "0", "note": "19集全", "actor": "陈圆,王子帅,郑淑贤,张小辉,赵千羽,胡波,杜鹏远,王慧丽,王新华,韩雪莲", "director": "孙峥", "dl": {"dd": {"@flag": "zuidam3u8", "#text": "第01集$http://shishang.dingxiangzuida.com/20200429/668_7e56c53a/index.m3u8$zuidam3u8#第02集$http://shishang.dingxiangzuida.com/20200429/665_e9141e55/index.m3u8$zuidam3u8#第03集$http://shishang.dingxiangzuida.com/20200429/664_15c8c57d/index.m3u8$zuidam3u8#第04集$http://shishang.dingxiangzuida.com/20200429/663_249867c1/index.m3u8$zuidam3u8#第05集$http://shishang.dingxiangzuida.com/20200429/662_a8f5b4ad/index.m3u8$zuidam3u8#第06集$http://shishang.dingxiangzuida.com/20200429/661_8446dbcf/index.m3u8$zuidam3u8#第07集$http://shishang.dingxiangzuida.com/20200429/660_fdcc96c8/index.m3u8$zuidam3u8#第08集$http://shishang.dingxiangzuida.com/20200429/659_081df03e/index.m3u8$zuidam3u8#第09集$http://shishang.dingxiangzuida.com/20200429/658_a667f96a/index.m3u8$zuidam3u8#第10集$http://shishang.dingxiangzuida.com/20200429/657_90603511/index.m3u8$zuidam3u8#第11集$http://shishang.dingxiangzuida.com/20200429/656_c1902538/index.m3u8$zuidam3u8#第12集$http://shishang.dingxiangzuida.com/20200429/655_0b1ba7e2/index.m3u8$zuidam3u8#第13集$http://shishang.dingxiangzuida.com/20200429/654_6cf3f82d/index.m3u8$zuidam3u8#第14集$http://shishang.dingxiangzuida.com/20200429/653_6b6b118e/index.m3u8$zuidam3u8#第15集$http://shishang.dingxiangzuida.com/20200429/652_d4f15bcf/index.m3u8$zuidam3u8#第16集$http://shishang.dingxiangzuida.com/20200429/651_580d161a/index.m3u8$zuidam3u8#第17集$http://shishang.dingxiangzuida.com/20200429/650_e2ad632f/index.m3u8$zuidam3u8#第18集$http://shishang.dingxiangzuida.com/20200429/649_bd9f4147/index.m3u8$zuidam3u8#第19集$http://shishang.dingxiangzuida.com/20200429/648_07bb0e47/index.m3u8$zuidam3u8"}}, "des": "莫小豆以为，所谓爱情，就该不顾一切、轰轰烈烈。为了倒追男神，她绞尽心思、花样百出。怎料，男神隐婚，她莫名成了人人不耻的小三！原配示威，男神践踏她的尊严、视她为粪土？她莫小豆也是有骨气的！结婚嘛，谁又不是嫁不出去。只是，没想到她闪婚的帅哥还是个有故事的好男人。两个为情所伤的人，开始了一段意想不到的婚姻生活……"}, {"last": "2020-04-30 16:37:21", "id": "84733", "tid": "12", "name": "深爱食堂", "type": "国产剧", "pic": "https://tu.tianzuida.com/pic/upload/vod/2020-04-29/202004291588126072.jpg", "lang": "国语", "area": "大陆", "year": "2014", "state": "0", "note": "10集全", "actor": "隋咏良,李茂,伊一,陈亦飞", "director": "宋月经", "dl": {"dd": {"@flag": "zuidam3u8", "#text": "第01集$http://shishang.dingxiangzuida.com/20200429/616_4d73d5a0/index.m3u8$zuidam3u8#第02集$http://shishang.dingxiangzuida.com/20200429/615_1203c886/index.m3u8$zuidam3u8#第03集$http://shishang.dingxiangzuida.com/20200429/614_fe1e34c2/index.m3u8$zuidam3u8#第04集$http://shishang.dingxiangzuida.com/20200429/613_9ce434af/index.m3u8$zuidam3u8#第05集$http://shishang.dingxiangzuida.com/20200429/612_47d1c915/index.m3u8$zuidam3u8#第06集$http://shishang.dingxiangzuida.com/20200429/611_a6d6ab47/index.m3u8$zuidam3u8#第07集$http://shishang.dingxiangzuida.com/20200429/610_2302376b/index.m3u8$zuidam3u8#第08集$http://shishang.dingxiangzuida.com/20200429/609_17f1960e/index.m3u8$zuidam3u8#第09集$http://shishang.dingxiangzuida.com/20200429/608_ac4d7e21/index.m3u8$zuidam3u8#第10集$http://shishang.dingxiangzuida.com/20200429/607_0f4471f7/index.m3u8$zuidam3u8"}}, "des": "父亲的胡辣汤【他是怎么当上官的】 他是个不大不小的父母官，膝下一个女儿。女儿结婚后一年半，时而说太忙不回娘家。次数多了，多少觉得有点奇怪。某夜，女儿哭着跑回来：被打得猪头一样……领导路过食堂，喝了几碗胡辣汤，去学校找到了女婿。女婿走近，领导同志一脚将他迎面踹倒……领导同志洗了一个澡，换了一身干净衣服，把材料备好，去自首…… 不加盐的小黄鱼【不加盐得腥成啥样】 漂亮傲娇的安妮小姐跟老板抱怨食堂的小黄鱼不新鲜，她的宠物猫咪咪很有意见。安妮隔三差五来店里打包不加盐的小黄鱼，老板是她的“猫御厨”。为了咪咪，安妮拒绝出差，换了份薪水低了很多的清闲工作，为咪咪举行生日会……在她心里，咪咪是她决不能失去的亲人，宁可放弃男朋友也不会抛弃咪咪的。突然有一天，咪咪不见了…… 回忆里的土豆丝饼【土豆丝饼换成庆丰包子也一样成立吧】 食堂里整整吃了三天的土豆丝饼，大家都快吃吐了。事情的起因源于一个叫米璐的美食记者的寻访。米其林的主厨轩辕常来食堂吃土豆丝饼，米璐使出浑身解数想套出背后的故事，但都被轩辕拒绝。某天，米璐突然说了句“大叔，您还记得十五年前那个被您打成重伤的人吗，他还活着”，轩辕惊吓无比……米璐似乎掌握了轩辕不为人知的秘密。 加红牛的红烧肉【请告诉我为什么有个“红”字就能放在一起】 “双红组合”（红烧肉+红牛）是广告平面设计师荣光的挚爱，加班标配，百吃不腻。荣光为楼盘地产做广告,加班是常事。遇上挑剔的客户，甚至陪标当炮灰，即便不甘心，他也只能默默忍耐。就在付出很多心血，独立操作的项目即将提案的前夕，荣光接到老家电话：爷爷过世。回去还是不回去，提案重要还是送爷爷最后一程重要，荣光犹豫不决。 加牛奶的蛋炒饭【那样做出来的应该只能算作是粥】 每周五晚，这个三十多岁的男人都会从工作的牧场背上新鲜的牛奶，坐着火车来到妻子生活的城市，周日再坐火车回去。结婚已三年，两地分居也有三年。周日分别前，他们总会来食堂点两份做起来最快的蛋炒饭，加入一点丈夫带来的牛奶，满屋弥漫着香甜的味道。得知丈夫把调来杭州的机会让给了别人，妻子极度失望之下提出离婚…… 插蜡烛的肉蒸蛋【我大胆地猜测接下来大家看到蛋仔身上所有的洞都插上了蜡烛然后做成了蒸肉】 因为喜欢肉蒸蛋，大家都叫他蛋仔。蛋仔是一个总接不到戏的小演员，混沌度日。和代驾认识的女友分手后，蛋仔在电玩城遇到一个10岁小魔头小贝，成为惺惺相惜的难兄难弟。某夜，小贝在食堂等妈妈来过生日。可是妈妈临时加班，情急之下小贝和蛋仔联合导演了一场小朋友绑架事件。当小贝的妈妈推开食堂的门，大家都惊呆了…… 桃花碗里的麻婆豆腐【所以桃花只能着落在麻婆身上了】 乔公子，男，女士内衣设计师。英姿，女，电视台家庭购物频道主持人。一个用右手，一个用左手，一个使筷子，一个用勺子，一个爱吃面，一个爱吃饭，一个是老板最欢迎的客人，一个是老板最害怕的客人，除了一点，都爱麻婆豆腐之外，他们真没什么相同之处了。都说男女之间没有纯友谊，天知道这南辕北辙的两个人是怎么成为闺蜜的…… 家香浓郁的黑芝麻糊【其实食堂的芝麻糊就是现冲的】 良会是电视购物频道的接线员，她希望能用最柔和的声音来接听每一个人的电话，尽自己所能去温暖每一颗心。良会十分喜欢食堂的手磨黑芝麻糊，暖暖的，有家的味道。良会的父母早就离婚了，家，对她而言似乎成了最奢侈的渴望。一位老大爷常打热线，聊起来没完没了，良会得知老大爷是孤巢老人，身边一个说话的人都没有…… 冠军味道的片儿川【我真不知道什么是片儿川】 小博是自行车运动员，训练结束后教练常带他来食堂吃饭。因为说过比赛赢了再吃片儿川这样的话，每次教练吃片儿川的时候，小博只能在一边看着咽口水。一次训练中，小博膝盖出现异样。医院查明小博膝盖受伤，不适合继续做剧烈运动，教练打算中止训练，小博却坚持参加比赛。比赛当天，一场抢劫事件破坏了小博的冠军之路…… 香味十足的臭豆腐【作为一个臭豆腐你失格了】 这个城市有那么多挣扎奋斗着的外乡人，湖南人董小姐十分钟爱食堂的臭豆腐。这里也是她相亲的主战场。告别了听妈妈的话的“奶瓶男”，又告别了事事把自己摆第一位的“上帝男”，董小姐又遇上了一个不主动、不拒绝、不负责的“三不文艺男”……经历了种种失败的相亲，董小姐随着春运大军离开了这座城市，她一个人去完成了那条计划了很久的蜜月旅行……"}, {"last": "2020-04-30 16:37:12", "id": "84734", "tid": "12", "name": "深爱食堂第二季", "type": "国产剧", "pic": "https://tu.tianzuida.com/pic/upload/vod/2020-04-29/202004291588126165.jpg", "lang": "国语", "area": "大陆", "year": "2016", "state": "0", "note": "13集全", "actor": "保剑锋,伊一,乔杉,潘辰,孙伟豪,于蓓蓓", "director": "杨永春,明焱", "dl": {"dd": {"@flag": "zuidam3u8", "#text": "第01集$http://shishang.dingxiangzuida.com/20200429/606_c6da29fb/index.m3u8$zuidam3u8#第02集$http://shishang.dingxiangzuida.com/20200429/605_b0bc2312/index.m3u8$zuidam3u8#第03集$http://shishang.dingxiangzuida.com/20200429/604_e025f189/index.m3u8$zuidam3u8#第04集$http://shishang.dingxiangzuida.com/20200429/603_07cfae8b/index.m3u8$zuidam3u8#第05集$http://shishang.dingxiangzuida.com/20200429/602_1215e8f3/index.m3u8$zuidam3u8#第06集$http://shishang.dingxiangzuida.com/20200429/601_46f43f09/index.m3u8$zuidam3u8#第07集$http://shishang.dingxiangzuida.com/20200429/600_7a634f2a/index.m3u8$zuidam3u8#第08集$http://shishang.dingxiangzuida.com/20200429/599_385b27dc/index.m3u8$zuidam3u8#第09集$http://shishang.dingxiangzuida.com/20200429/598_f9b323e4/index.m3u8$zuidam3u8#第10集$http://shishang.dingxiangzuida.com/20200429/597_c1690020/index.m3u8$zuidam3u8#第11集$http://shishang.dingxiangzuida.com/20200429/596_60cb2172/index.m3u8$zuidam3u8#第12集$http://shishang.dingxiangzuida.com/20200429/595_8e962c75/index.m3u8$zuidam3u8#第13集$http://shishang.dingxiangzuida.com/20200429/594_46ca3756/index.m3u8$zuidam3u8"}}, "des": "主要以几个小故事串接而成，这些故事均是发生在一家有特色的“深爱食堂”中，剧情通过美食而发展，这里就像是每一个孤独灵魂的家，来往顾客纷纷讲述着自己的情感纠葛，以最真诚、质朴的交流互动向观众展现都市年轻人积极向上、励志奋斗的感人经历。"}, {"last": "2020-04-30 16:38:34", "id": "84735", "tid": "12", "name": "爱的追踪", "type": "国产剧", "pic": "https://tu.tianzuida.com/pic/upload/vod/2020-04-29/202004291588126620.jpg", "lang": "国语", "area": "大陆", "year": "2016", "state": "0", "note": "36集全", "actor": "张国立,闫妮,高晓菲,高玉庆,谭洋,刘立,初俊辰,周建鹏,孙铱,樊昱君,曾肖龙,朱怀旭,孙岚,郑业成,郑强", "director": "张国立,陈昆晖", "dl": {"dd": {"@flag": "zuidam3u8", "#text": "第01集$http://shishang.dingxiangzuida.com/20200429/718_1df9e81c/index.m3u8$zuidam3u8#第02集$http://shishang.dingxiangzuida.com/20200429/717_c85e9578/index.m3u8$zuidam3u8#第03集$http://shishang.dingxiangzuida.com/20200429/716_d83ad135/index.m3u8$zuidam3u8#第04集$http://shishang.dingxiangzuida.com/20200429/715_a9a73b2d/index.m3u8$zuidam3u8#第05集$http://shishang.dingxiangzuida.com/20200429/714_7077bcef/index.m3u8$zuidam3u8#第06集$http://shishang.dingxiangzuida.com/20200429/713_c3afa5b0/index.m3u8$zuidam3u8#第07集$http://shishang.dingxiangzuida.com/20200429/712_295bcc20/index.m3u8$zuidam3u8#第08集$http://shishang.dingxiangzuida.com/20200429/711_173f1c64/index.m3u8$zuidam3u8#第09集$http://shishang.dingxiangzuida.com/20200429/710_e2ab89c6/index.m3u8$zuidam3u8#第10集$http://shishang.dingxiangzuida.com/20200429/709_c1aa84b4/index.m3u8$zuidam3u8#第11集$http://shishang.dingxiangzuida.com/20200429/708_e735b0e4/index.m3u8$zuidam3u8#第12集$http://shishang.dingxiangzuida.com/20200429/707_c653c84d/index.m3u8$zuidam3u8#第13集$http://shishang.dingxiangzuida.com/20200429/706_06268f5b/index.m3u8$zuidam3u8#第14集$http://shishang.dingxiangzuida.com/20200429/705_e194c856/index.m3u8$zuidam3u8#第15集$http://shishang.dingxiangzuida.com/20200429/704_fd81ea66/index.m3u8$zuidam3u8#第16集$http://shishang.dingxiangzuida.com/20200429/703_80c9e419/index.m3u8$zuidam3u8#第17集$http://shishang.dingxiangzuida.com/20200429/702_455f96f5/index.m3u8$zuidam3u8#第18集$http://shishang.dingxiangzuida.com/20200429/701_3635d24b/index.m3u8$zuidam3u8#第19集$http://shishang.dingxiangzuida.com/20200429/700_f478bf01/index.m3u8$zuidam3u8#第20集$http://shishang.dingxiangzuida.com/20200429/699_f90d7fd9/index.m3u8$zuidam3u8#第21集$http://shishang.dingxiangzuida.com/20200429/698_8b4baf32/index.m3u8$zuidam3u8#第22集$http://shishang.dingxiangzuida.com/20200429/697_3db870c7/index.m3u8$zuidam3u8#第23集$http://shishang.dingxiangzuida.com/20200429/696_3b3c157b/index.m3u8$zuidam3u8#第24集$http://shishang.dingxiangzuida.com/20200429/695_822943d0/index.m3u8$zuidam3u8#第25集$http://shishang.dingxiangzuida.com/20200429/694_868f5b07/index.m3u8$zuidam3u8#第26集$http://shishang.dingxiangzuida.com/20200429/693_9e8bfe99/index.m3u8$zuidam3u8#第27集$http://shishang.dingxiangzuida.com/20200429/692_cd604a7b/index.m3u8$zuidam3u8#第28集$http://shishang.dingxiangzuida.com/20200429/691_fac6ce53/index.m3u8$zuidam3u8#第29集$http://shishang.dingxiangzuida.com/20200429/690_919a5118/index.m3u8$zuidam3u8#第30集$http://shishang.dingxiangzuida.com/20200429/689_d57fac40/index.m3u8$zuidam3u8#第31集$http://shishang.dingxiangzuida.com/20200429/688_6e8f091d/index.m3u8$zuidam3u8#第32集$http://shishang.dingxiangzuida.com/20200429/687_887b600d/index.m3u8$zuidam3u8#第33集$http://shishang.dingxiangzuida.com/20200429/686_0359cd1a/index.m3u8$zuidam3u8#第34集$http://shishang.dingxiangzuida.com/20200429/685_24826887/index.m3u8$zuidam3u8#第35集$http://shishang.dingxiangzuida.com/20200429/684_ea313064/index.m3u8$zuidam3u8#第36集$http://shishang.dingxiangzuida.com/20200429/683_612ada34/index.m3u8$zuidam3u8"}}, "des": "在中国经济大潮风起云涌之时，两个情同手足的异姓兄弟马德庆和张文昊的人生也进入了拐点。身为刑警队长的哥哥马德庆被调往了刚成立的经侦大队，顿觉英雄无用武之地，更令他懊恼的是弟弟张文昊一意孤行，放弃公职投入商海，接二连三惹出事端。张文昊生意赔了，他以同样的骗术嫁祸于下家得以翻盘，但受害方却因此自杀，张文昊的精心设计使他逃脱了法律的惩罚，马德庆此时也意识到经侦工作任重道远。此后经年，两兄弟一个成为了热衷慈善的商界大腭，一个成为了经侦队伍的领头羊。然而原罪的阴影却一直让兄弟二人处于情与法的纠葛与较量中。马德庆始终用自己的方法帮助和警醒着弟弟不要触及法律边线，但对噩梦的回避和对欲望的追逐，最终使张文昊毁了身边人，也毁了哥哥的家庭幸福。当一切尘埃落定，张文昊在马德庆的陪伴下终于走向了赎罪之门。"}, {"last": "2020-04-30 16:38:22", "id": "84736", "tid": "12", "name": "五鼠闹东京", "type": "国产剧", "pic": "https://tu.tianzuida.com/pic/upload/vod/2020-04-29/202004291588126705.jpg", "lang": "国语", "area": "大陆", "year": "2016", "state": "0", "note": "44集全", "actor": "陈晓,严屹宽,郑爽,张芷溪,谢宁,王茂蕾,梁冠华,马书良,刘德凯,李鑫雨,李添诺,王大奇,张维娜", "director": "吴家骀", "dl": {"dd": {"@flag": "zuidam3u8", "#text": "第01集$http://shishang.dingxiangzuida.com/20200429/553_6bac141d/index.m3u8$zuidam3u8#第02集$http://shishang.dingxiangzuida.com/20200429/552_a84ee753/index.m3u8$zuidam3u8#第03集$http://shishang.dingxiangzuida.com/20200429/551_af00547c/index.m3u8$zuidam3u8#第04集$http://shishang.dingxiangzuida.com/20200429/550_7e4479b7/index.m3u8$zuidam3u8#第05集$http://shishang.dingxiangzuida.com/20200429/549_8b684674/index.m3u8$zuidam3u8#第06集$http://shishang.dingxiangzuida.com/20200429/548_113181a7/index.m3u8$zuidam3u8#第07集$http://shishang.dingxiangzuida.com/20200429/547_7064cef5/index.m3u8$zuidam3u8#第08集$http://shishang.dingxiangzuida.com/20200429/546_13f362d4/index.m3u8$zuidam3u8#第09集$http://shishang.dingxiangzuida.com/20200429/545_5585f4c4/index.m3u8$zuidam3u8#第10集$http://shishang.dingxiangzuida.com/20200429/544_cd5c22d1/index.m3u8$zuidam3u8#第11集$http://shishang.dingxiangzuida.com/20200429/543_b8d605b5/index.m3u8$zuidam3u8#第12集$http://shishang.dingxiangzuida.com/20200429/542_264889c1/index.m3u8$zuidam3u8#第13集$http://shishang.dingxiangzuida.com/20200429/541_ad8e8d57/index.m3u8$zuidam3u8#第14集$http://shishang.dingxiangzuida.com/20200429/540_45868e09/index.m3u8$zuidam3u8#第15集$http://shishang.dingxiangzuida.com/20200429/539_a8a7b381/index.m3u8$zuidam3u8#第16集$http://shishang.dingxiangzuida.com/20200429/538_b47b76b8/index.m3u8$zuidam3u8#第17集$http://shishang.dingxiangzuida.com/20200429/537_ac05a3b8/index.m3u8$zuidam3u8#第18集$http://shishang.dingxiangzuida.com/20200429/536_3790b31a/index.m3u8$zuidam3u8#第19集$http://shishang.dingxiangzuida.com/20200429/535_1f73ac99/index.m3u8$zuidam3u8#第20集$http://shishang.dingxiangzuida.com/20200429/534_308b58e2/index.m3u8$zuidam3u8#第21集$http://shishang.dingxiangzuida.com/20200429/533_1bd2f492/index.m3u8$zuidam3u8#第22集$http://shishang.dingxiangzuida.com/20200429/532_ad145b7e/index.m3u8$zuidam3u8#第23集$http://shishang.dingxiangzuida.com/20200429/531_bc1cb2c1/index.m3u8$zuidam3u8#第24集$http://shishang.dingxiangzuida.com/20200429/530_474d611c/index.m3u8$zuidam3u8#第25集$http://shishang.dingxiangzuida.com/20200429/529_a0a4c7bd/index.m3u8$zuidam3u8#第26集$http://shishang.dingxiangzuida.com/20200429/528_3032efd7/index.m3u8$zuidam3u8#第27集$http://shishang.dingxiangzuida.com/20200429/527_991b3ff7/index.m3u8$zuidam3u8#第28集$http://shishang.dingxiangzuida.com/20200429/526_1bdee4f5/index.m3u8$zuidam3u8#第29集$http://shishang.dingxiangzuida.com/20200429/525_a403fac4/index.m3u8$zuidam3u8#第30集$http://shishang.dingxiangzuida.com/20200429/524_cc034e67/index.m3u8$zuidam3u8#第31集$http://shishang.dingxiangzuida.com/20200429/523_eeee74fa/index.m3u8$zuidam3u8#第32集$http://shishang.dingxiangzuida.com/20200429/522_75eb6f6c/index.m3u8$zuidam3u8#第33集$http://shishang.dingxiangzuida.com/20200429/521_909012b5/index.m3u8$zuidam3u8#第34集$http://shishang.dingxiangzuida.com/20200429/520_f9b8f273/index.m3u8$zuidam3u8#第35集$http://shishang.dingxiangzuida.com/20200429/519_2410d920/index.m3u8$zuidam3u8#第36集$http://shishang.dingxiangzuida.com/20200429/518_cc51d5c8/index.m3u8$zuidam3u8#第37集$http://shishang.dingxiangzuida.com/20200429/517_13f8c117/index.m3u8$zuidam3u8#第38集$http://shishang.dingxiangzuida.com/20200429/516_ce1ce031/index.m3u8$zuidam3u8#第39集$http://shishang.dingxiangzuida.com/20200429/515_dd6600f7/index.m3u8$zuidam3u8#第40集$http://shishang.dingxiangzuida.com/20200429/514_dae016e2/index.m3u8$zuidam3u8#第41集$http://shishang.dingxiangzuida.com/20200429/513_3723353a/index.m3u8$zuidam3u8#第42集$http://shishang.dingxiangzuida.com/20200429/512_c549d3a6/index.m3u8$zuidam3u8#第43集$http://shishang.dingxiangzuida.com/20200429/511_0433ef40/index.m3u8$zuidam3u8#第44集$http://shishang.dingxiangzuida.com/20200429/510_c6fc627b/index.m3u8$zuidam3u8"}}, "des": "故事发生在北宋仁宗年间，开封府尹包拯包青天（梁冠华 饰）秉公执法，不畏强权豪梁，由此深受以庞太师为首的一干恶人的嫉恨。在追查黑虎寨期间，身处凶险之中的包大人为侠客展昭（严屹宽 饰）救下。回到京城后，展雄飞在皇帝面前展示了自己的一身绝学，最终被帝王赐号“御猫”，却由此惹出新的麻烦。话说在远离京师的陷空岛住着五位侠客，分别是钻天鼠卢方（何瑜 饰）、彻地鼠韩彰（王大奇 饰）、穿山鼠徐庆（谢宁 饰）、翻江鼠蒋平（王茂蕾 饰）以及锦毛鼠白玉堂（陈晓 饰），他们身怀绝技，合称“五鼠”。心高气傲的白玉堂恼恨展昭的御猫绰号，非要进京与之较量一番，由此引出了“五鼠闹东京”的传奇故事…… 本片根据古典名著《三侠五义》改编。"}, {"last": "2020-04-30 16:38:08", "id": "84737", "tid": "12", "name": "咱们相爱吧", "type": "国产剧", "pic": "https://tu.tianzuida.com/pic/upload/vod/2020-04-29/202004291588126849.jpg", "lang": "国语", "area": "大陆", "year": "2016", "state": "0", "note": "58集全", "actor": "张静初,张歆艺,秦岚,袁弘,明道,张晞临,奇道,柳小海,董维嘉,杨青,盖克,马程程", "director": "刘江", "dl": {"dd": {"@flag": "zuidam3u8", "#text": "第01集$http://shishang.dingxiangzuida.com/20200429/466_f433cf84/index.m3u8$zuidam3u8#第02集$http://shishang.dingxiangzuida.com/20200429/465_31e511c2/index.m3u8$zuidam3u8#第03集$http://shishang.dingxiangzuida.com/20200429/464_e91aca2c/index.m3u8$zuidam3u8#第04集$http://shishang.dingxiangzuida.com/20200429/463_5143885d/index.m3u8$zuidam3u8#第05集$http://shishang.dingxiangzuida.com/20200429/462_66d73eee/index.m3u8$zuidam3u8#第06集$http://shishang.dingxiangzuida.com/20200429/461_11a39795/index.m3u8$zuidam3u8#第07集$http://shishang.dingxiangzuida.com/20200429/460_45fd000f/index.m3u8$zuidam3u8#第08集$http://shishang.dingxiangzuida.com/20200429/459_a5944136/index.m3u8$zuidam3u8#第09集$http://shishang.dingxiangzuida.com/20200429/458_9e399778/index.m3u8$zuidam3u8#第10集$http://shishang.dingxiangzuida.com/20200429/457_a6dadd1b/index.m3u8$zuidam3u8#第11集$http://shishang.dingxiangzuida.com/20200429/456_0c65a26c/index.m3u8$zuidam3u8#第12集$http://shishang.dingxiangzuida.com/20200429/455_d7666e1a/index.m3u8$zuidam3u8#第13集$http://shishang.dingxiangzuida.com/20200429/454_0a054114/index.m3u8$zuidam3u8#第14集$http://shishang.dingxiangzuida.com/20200429/453_2a5b414d/index.m3u8$zuidam3u8#第15集$http://shishang.dingxiangzuida.com/20200429/452_b1cd47f9/index.m3u8$zuidam3u8#第16集$http://shishang.dingxiangzuida.com/20200429/451_d44de5ce/index.m3u8$zuidam3u8#第17集$http://shishang.dingxiangzuida.com/20200429/450_9e31b3e6/index.m3u8$zuidam3u8#第18集$http://shishang.dingxiangzuida.com/20200429/449_c642b194/index.m3u8$zuidam3u8#第19集$http://shishang.dingxiangzuida.com/20200429/448_897968cf/index.m3u8$zuidam3u8#第20集$http://shishang.dingxiangzuida.com/20200429/447_250b6fef/index.m3u8$zuidam3u8#第21集$http://shishang.dingxiangzuida.com/20200429/446_8f509503/index.m3u8$zuidam3u8#第22集$http://shishang.dingxiangzuida.com/20200429/445_e9778ddb/index.m3u8$zuidam3u8#第23集$http://shishang.dingxiangzuida.com/20200429/444_fde57a69/index.m3u8$zuidam3u8#第24集$http://shishang.dingxiangzuida.com/20200429/443_b47e2a61/index.m3u8$zuidam3u8#第25集$http://shishang.dingxiangzuida.com/20200429/442_08225671/index.m3u8$zuidam3u8#第26集$http://shishang.dingxiangzuida.com/20200429/441_36819750/index.m3u8$zuidam3u8#第27集$http://shishang.dingxiangzuida.com/20200429/440_3375e69d/index.m3u8$zuidam3u8#第28集$http://shishang.dingxiangzuida.com/20200429/439_a7ba0eb2/index.m3u8$zuidam3u8#第29集$http://shishang.dingxiangzuida.com/20200429/438_1b7a402b/index.m3u8$zuidam3u8#第30集$http://shishang.dingxiangzuida.com/20200429/437_4db241f2/index.m3u8$zuidam3u8#第31集$http://shishang.dingxiangzuida.com/20200429/436_484fcba5/index.m3u8$zuidam3u8#第32集$http://shishang.dingxiangzuida.com/20200429/435_2841b71b/index.m3u8$zuidam3u8#第33集$http://shishang.dingxiangzuida.com/20200429/434_a5f4a797/index.m3u8$zuidam3u8#第34集$http://shishang.dingxiangzuida.com/20200429/433_bc2be3ea/index.m3u8$zuidam3u8#第35集$http://shishang.dingxiangzuida.com/20200429/432_b8c1c3f3/index.m3u8$zuidam3u8#第36集$http://shishang.dingxiangzuida.com/20200429/431_ed5f447b/index.m3u8$zuidam3u8#第37集$http://shishang.dingxiangzuida.com/20200429/430_a1b7f8bc/index.m3u8$zuidam3u8#第38集$http://shishang.dingxiangzuida.com/20200429/429_e5b0aec8/index.m3u8$zuidam3u8#第39集$http://shishang.dingxiangzuida.com/20200429/428_219972d0/index.m3u8$zuidam3u8#第40集$http://shishang.dingxiangzuida.com/20200429/427_d0879c46/index.m3u8$zuidam3u8#第41集$http://shishang.dingxiangzuida.com/20200429/426_bad2074f/index.m3u8$zuidam3u8#第42集$http://shishang.dingxiangzuida.com/20200429/425_90c3618e/index.m3u8$zuidam3u8#第43集$http://shishang.dingxiangzuida.com/20200429/424_68b18502/index.m3u8$zuidam3u8#第44集$http://shishang.dingxiangzuida.com/20200429/423_02f847d2/index.m3u8$zuidam3u8#第45集$http://shishang.dingxiangzuida.com/20200429/422_060c49e3/index.m3u8$zuidam3u8#第46集$http://shishang.dingxiangzuida.com/20200429/421_c5e390f1/index.m3u8$zuidam3u8#第47集$http://shishang.dingxiangzuida.com/20200429/420_d57610ab/index.m3u8$zuidam3u8#第48集$http://shishang.dingxiangzuida.com/20200429/419_cbd394b6/index.m3u8$zuidam3u8#第49集$http://shishang.dingxiangzuida.com/20200429/418_8bb5de22/index.m3u8$zuidam3u8#第50集$http://shishang.dingxiangzuida.com/20200429/417_24186447/index.m3u8$zuidam3u8#第51集$http://shishang.dingxiangzuida.com/20200429/416_4177e8ab/index.m3u8$zuidam3u8#第52集$http://shishang.dingxiangzuida.com/20200429/415_357802de/index.m3u8$zuidam3u8#第53集$http://shishang.dingxiangzuida.com/20200429/414_bedeb888/index.m3u8$zuidam3u8#第54集$http://shishang.dingxiangzuida.com/20200429/413_c47ed31d/index.m3u8$zuidam3u8#第55集$http://shishang.dingxiangzuida.com/20200429/412_6db93301/index.m3u8$zuidam3u8#第56集$http://shishang.dingxiangzuida.com/20200429/411_7b76f9a0/index.m3u8$zuidam3u8#第57集$http://shishang.dingxiangzuida.com/20200429/410_fdeb8da2/index.m3u8$zuidam3u8#第58集$http://shishang.dingxiangzuida.com/20200429/409_81c3340d/index.m3u8$zuidam3u8"}}, "des": "林笑笑（张静初 饰）、潘芝芝（张歆艺 饰）和蔡春妮（秦岚 饰）是从小玩到大的好友，三人个性虽然迥异，友情上亦有着各种磕磕碰碰，但到底是相互扶持着一路走来的同伴，彼此之间友谊十分坚实。林笑笑固执死板的个性让她在职场和情场上都吃了大亏，不仅离了婚丢掉了工作，还必须独自肩负起抚养儿子的重任。 某日，林笑笑邂逅了名为时光（袁弘 饰）的建筑师，袁弘被林笑笑的坚强和乐观深深吸引，两人之间的关系越走越近。然而，令林笑笑没有想到的是，潘芝芝竟然也疯狂的喜欢上了时光，与此同时，儿子对母亲的新恋情表现出了强烈的抵触，一时之间，林笑笑不知道该做出怎样的选择。"}, {"last": "2020-04-30 16:37:50", "id": "84738", "tid": "12", "name": "超能姐姐大作战", "type": "国产剧", "pic": "https://tu.tianzuida.com/pic/upload/vod/2020-04-29/202004291588126972.jpg", "lang": "国语", "area": "大陆", "year": "2016", "state": "0", "note": "16集全", "actor": "瓜尔佳泽,赵奕欢", "director": "未知", "dl": {"dd": {"@flag": "zuidam3u8", "#text": "第01集$http://shishang.dingxiangzuida.com/20200429/682_27d94fe4/index.m3u8$zuidam3u8#第02集$http://shishang.dingxiangzuida.com/20200429/681_cc29d9ca/index.m3u8$zuidam3u8#第03集$http://shishang.dingxiangzuida.com/20200429/680_2c79d7f2/index.m3u8$zuidam3u8#第04集$http://shishang.dingxiangzuida.com/20200429/679_e2150540/index.m3u8$zuidam3u8#第05集$http://shishang.dingxiangzuida.com/20200429/678_85e042cf/index.m3u8$zuidam3u8#第06集$http://shishang.dingxiangzuida.com/20200429/677_a34ce3ee/index.m3u8$zuidam3u8#第07集$http://shishang.dingxiangzuida.com/20200429/676_08c5c50f/index.m3u8$zuidam3u8#第08集$http://shishang.dingxiangzuida.com/20200429/675_35d5b09f/index.m3u8$zuidam3u8#第09集$http://shishang.dingxiangzuida.com/20200429/674_ce66f2c4/index.m3u8$zuidam3u8#第10集$http://shishang.dingxiangzuida.com/20200429/673_08317074/index.m3u8$zuidam3u8#第11集$http://shishang.dingxiangzuida.com/20200429/672_6083c11e/index.m3u8$zuidam3u8#第12集$http://shishang.dingxiangzuida.com/20200429/671_a023cedf/index.m3u8$zuidam3u8#第13集$http://shishang.dingxiangzuida.com/20200429/670_4652fa9e/index.m3u8$zuidam3u8#第14集$http://shishang.dingxiangzuida.com/20200429/669_2e775f62/index.m3u8$zuidam3u8#第15集$http://shishang.dingxiangzuida.com/20200429/667_3c9869bd/index.m3u8$zuidam3u8#第16集$http://shishang.dingxiangzuida.com/20200429/666_fe7b2a17/index.m3u8$zuidam3u8"}}, "des": "《聊宅：超能姐姐大作战》是一部陕西文投艺达投资有限公司、腾讯视频联合出品大型魔幻网络巨制，聊宅：超能姐姐大作战由鬼才编剧万麟历时三年精心打造，国内一线商业女导演宋媚执导，新生代演员瓜尔佳泽和有着“宅男女神”之称的赵奕欢领衔主演。据悉，新生代演员瓜尔佳泽将饰演超现代宅男“腌翅侠”，赵奕欢将饰演九而。"}, {"last": "2020-04-30 16:37:34", "id": "84739", "tid": "12", "name": "天伦", "type": "国产剧", "pic": "https://tu.tianzuida.com/pic/upload/vod/2020-04-29/202004291588127135.jpg", "lang": "国语", "area": "大陆", "year": "2016", "state": "0", "note": "40集全", "actor": "陈小艺,练练,马丽,张国庆,陈思斯,陆纪依,刘亭作,崔林,江昊桐,刘梦轩,陈婷", "director": "滕文骥,王为", "dl": {"dd": {"@flag": "zuidam3u8", "#text": "第01集$http://shishang.dingxiangzuida.com/20200429/593_2a3cca06/index.m3u8$zuidam3u8#第02集$http://shishang.dingxiangzuida.com/20200429/592_6b2b2f1e/index.m3u8$zuidam3u8#第03集$http://shishang.dingxiangzuida.com/20200429/591_cfc92138/index.m3u8$zuidam3u8#第04集$http://shishang.dingxiangzuida.com/20200429/590_0aa4a96a/index.m3u8$zuidam3u8#第05集$http://shishang.dingxiangzuida.com/20200429/589_d6f59be2/index.m3u8$zuidam3u8#第06集$http://shishang.dingxiangzuida.com/20200429/588_22fc3a5f/index.m3u8$zuidam3u8#第07集$http://shishang.dingxiangzuida.com/20200429/587_3f4064b8/index.m3u8$zuidam3u8#第08集$http://shishang.dingxiangzuida.com/20200429/586_f650228a/index.m3u8$zuidam3u8#第09集$http://shishang.dingxiangzuida.com/20200429/585_315a4a57/index.m3u8$zuidam3u8#第10集$http://shishang.dingxiangzuida.com/20200429/584_f862227f/index.m3u8$zuidam3u8#第11集$http://shishang.dingxiangzuida.com/20200429/583_b20646a9/index.m3u8$zuidam3u8#第12集$http://shishang.dingxiangzuida.com/20200429/582_8685faa2/index.m3u8$zuidam3u8#第13集$http://shishang.dingxiangzuida.com/20200429/581_1ee374f5/index.m3u8$zuidam3u8#第14集$http://shishang.dingxiangzuida.com/20200429/580_d8ba28bc/index.m3u8$zuidam3u8#第15集$http://shishang.dingxiangzuida.com/20200429/579_bf6efd73/index.m3u8$zuidam3u8#第16集$http://shishang.dingxiangzuida.com/20200429/578_c2fb0389/index.m3u8$zuidam3u8#第17集$http://shishang.dingxiangzuida.com/20200429/577_1ea3bc61/index.m3u8$zuidam3u8#第18集$http://shishang.dingxiangzuida.com/20200429/576_2145de1a/index.m3u8$zuidam3u8#第19集$http://shishang.dingxiangzuida.com/20200429/575_1bc3beb5/index.m3u8$zuidam3u8#第20集$http://shishang.dingxiangzuida.com/20200429/574_68508ec6/index.m3u8$zuidam3u8#第21集$http://shishang.dingxiangzuida.com/20200429/573_c4e6764c/index.m3u8$zuidam3u8#第22集$http://shishang.dingxiangzuida.com/20200429/572_def6f19f/index.m3u8$zuidam3u8#第23集$http://shishang.dingxiangzuida.com/20200429/571_2e59a1e5/index.m3u8$zuidam3u8#第24集$http://shishang.dingxiangzuida.com/20200429/570_57b200c6/index.m3u8$zuidam3u8#第25集$http://shishang.dingxiangzuida.com/20200429/569_edf68354/index.m3u8$zuidam3u8#第26集$http://shishang.dingxiangzuida.com/20200429/568_c0fb622a/index.m3u8$zuidam3u8#第27集$http://shishang.dingxiangzuida.com/20200429/567_e6365140/index.m3u8$zuidam3u8#第28集$http://shishang.dingxiangzuida.com/20200429/566_7a85c0cc/index.m3u8$zuidam3u8#第29集$http://shishang.dingxiangzuida.com/20200429/565_ee0a9400/index.m3u8$zuidam3u8#第30集$http://shishang.dingxiangzuida.com/20200429/564_c0d4ca63/index.m3u8$zuidam3u8#第31集$http://shishang.dingxiangzuida.com/20200429/563_d592fd86/index.m3u8$zuidam3u8#第32集$http://shishang.dingxiangzuida.com/20200429/562_b0e94013/index.m3u8$zuidam3u8#第33集$http://shishang.dingxiangzuida.com/20200429/561_4780dc22/index.m3u8$zuidam3u8#第34集$http://shishang.dingxiangzuida.com/20200429/560_ed710c7f/index.m3u8$zuidam3u8#第35集$http://shishang.dingxiangzuida.com/20200429/559_70022673/index.m3u8$zuidam3u8#第36集$http://shishang.dingxiangzuida.com/20200429/558_59b290bf/index.m3u8$zuidam3u8#第37集$http://shishang.dingxiangzuida.com/20200429/557_2c21212a/index.m3u8$zuidam3u8#第38集$http://shishang.dingxiangzuida.com/20200429/556_a1775345/index.m3u8$zuidam3u8#第39集$http://shishang.dingxiangzuida.com/20200429/555_7b2bb224/index.m3u8$zuidam3u8#第40集$http://shishang.dingxiangzuida.com/20200429/554_58158a09/index.m3u8$zuidam3u8"}}, "des": "讲述“丁香”为主线的裴家几经坎坷的家族变迁。"}, {"last": "2020-10-14 11:45:51", "id": "84740", "tid": "4", "name": "万渣朝凰第2季", "type": "动漫片", "pic": "https://tu.tianzuida.com/pic/upload/vod/2020-04-29/202004291588127149.jpg", "lang": "国语", "area": "大陆", "year": "2020", "state": "0", "note": "更新到26集", "actor": "内详", "director": "未知", "dl": {"dd": {"@flag": "zuidam3u8", "#text": "第01集$http://yuledy.helanzuida.com/20200428/3218_47cbd1be/index.m3u8$zuidam3u8#第02集$http://yuledy.helanzuida.com/20200428/3217_0b43682b/index.m3u8$zuidam3u8#第03集$http://xigua-cdn.haima-zuida.com/20200505/6814_c4ef2a2c/index.m3u8$zuidam3u8#第04集$http://xigua-cdn.haima-zuida.com/20200512/7150_b337c4ef/index.m3u8$zuidam3u8#第05集$http://xigua-cdn.haima-zuida.com/20200519/7342_57e50974/index.m3u8$zuidam3u8#第06集$http://douban.donghongzuida.com/20200527/2628_ad5ea951/index.m3u8$zuidam3u8#第07集$http://douban.donghongzuida.com/20200603/3007_8a5cacc6/index.m3u8$zuidam3u8#第08集$http://yuledy.helanzuida.com/20200609/5632_ab042f13/index.m3u8$zuidam3u8#第09集$http://yuledy.helanzuida.com/20200616/6030_d3e940ca/index.m3u8$zuidam3u8#第10集$http://yuledy.helanzuida.com/20200623/6363_75f22105/index.m3u8$zuidam3u8#第11集$http://douban.donghongzuida.com/20200701/4661_948bd1bc/index.m3u8$zuidam3u8#第12集$http://douban.donghongzuida.com/20200708/5033_559b75c3/index.m3u8$zuidam3u8#第13集$http://xigua-cdn.haima-zuida.com/20200714/9185_9b146383/index.m3u8$zuidam3u8#第14集$http://xigua-cdn.haima-zuida.com/20200721/9337_284392ff/index.m3u8$zuidam3u8#第15集$http://douban.donghongzuida.com/20200729/6331_c464f9b7/index.m3u8$zuidam3u8#第16集$http://douban.donghongzuida.com/20200805/6785_91b5b2e8/index.m3u8$zuidam3u8#第17集$http://douban.donghongzuida.com/20200812/7215_45ecc9d6/index.m3u8$zuidam3u8#第18集$http://douban.donghongzuida.com/20200819/7722_a76ec50b/index.m3u8$zuidam3u8#第19集$http://douban.donghongzuida.com/20200826/8256_5cad2552/index.m3u8$zuidam3u8#第20集$http://yuledy.helanzuida.com/20200901/9871_b5caac91/index.m3u8$zuidam3u8#第21集$http://douban.donghongzuida.com/20200909/9212_d4e04378/index.m3u8$zuidam3u8#第22集$http://yuledy.helanzuida.com/20200918/11163_a00e9410/index.m3u8$zuidam3u8#第23集$http://xigua-cdn.haima-zuida.com/20200923/14598_f2bb3ec3/index.m3u8$zuidam3u8#第24集$http://yuledy.helanzuida.com/20200929/12006_d6937df7/index.m3u8$zuidam3u8#第25集$http://yuledy.helanzuida.com/20201006/12360_928d1622/index.m3u8$zuidam3u8#第26集$http://yuledy.helanzuida.com/20201013/12704_03cbfd30/index.m3u8$zuidam3u8"}}, "des": "无数女配受尽困扰，谁说女配只能悲惨下场？ 就看苏绿夏继续逆袭为其伸张正义！凭借缜密的思维逻辑，沉着冷静的应对改变女配悲惨人生的故事。想不到的大翻转，令人称赞的大逆袭！苏绿夏：“哼，不会做人是吗，我来教你啊”系统：“宿主大人，渣男遇见你真是太惨了”"}, {"last": "2020-04-30 16:37:00", "id": "84741", "tid": "12", "name": "女大学生宿舍", "type": "国产剧", "pic": "https://tu.tianzuida.com/pic/upload/vod/2020-04-29/202004291588127923.jpg", "lang": "国语", "area": "大陆", "year": "2016", "state": "0", "note": "10集全", "actor": "章方然,宁婧,李妍君,刘君军,王浩凯", "director": "金宜鸿,于方", "dl": {"dd": {"@flag": "zuidam3u8", "#text": "第01集$http://shishang.dingxiangzuida.com/20200429/636_a58d2257/index.m3u8$zuidam3u8#第02集$http://shishang.dingxiangzuida.com/20200429/635_83ee0a6f/index.m3u8$zuidam3u8#第03集$http://shishang.dingxiangzuida.com/20200429/634_bd21aa36/index.m3u8$zuidam3u8#第04集$http://shishang.dingxiangzuida.com/20200429/633_8d65fbf1/index.m3u8$zuidam3u8#第05集$http://shishang.dingxiangzuida.com/20200429/632_7556cd92/index.m3u8$zuidam3u8#第06集$http://shishang.dingxiangzuida.com/20200429/631_e116b672/index.m3u8$zuidam3u8#第07集$http://shishang.dingxiangzuida.com/20200429/630_6d60b687/index.m3u8$zuidam3u8#第08集$http://shishang.dingxiangzuida.com/20200429/629_bc5a0db1/index.m3u8$zuidam3u8#第09集$http://shishang.dingxiangzuida.com/20200429/628_4f68a0b2/index.m3u8$zuidam3u8#第10集$http://shishang.dingxiangzuida.com/20200429/627_35da0dbe/index.m3u8$zuidam3u8"}}, "des": "初入大学殿堂，同为艺术学院学生的夏丽叶、林朵、莫小邪、秦妮被分在同一宿舍，开始了互相磨合、逐渐理解包容的成长之路。爱慕虚荣、脾气暴躁的夏丽叶另有苦衷，乖乖女林朵居然有难以启齿的过往，柴禾妞秦妮看似大大咧咧实则大智若愚，大小姐出身的莫小邪扮演仗义女侠，默默付出......每个人的秘密和误会逐渐被解开。"}, {"last": "2020-04-30 16:36:48", "id": "84742", "tid": "12", "name": "硬骨头", "type": "国产剧", "pic": "https://tu.tianzuida.com/pic/upload/vod/2020-04-29/202004291588128064.jpg", "lang": "国语", "area": "大陆", "year": "2016", "state": "0", "note": "43集全", "actor": "吴其江,王强,李梅可,褚峰,郭东文,葛玟希,王奕盛,王俊彭,周建鹏", "director": "马跃千", "dl": {"dd": {"@flag": "zuidam3u8", "#text": "第01集$http://shishang.dingxiangzuida.com/20200429/509_adcf22d4/index.m3u8$zuidam3u8#第02集$http://shishang.dingxiangzuida.com/20200429/508_3ff61344/index.m3u8$zuidam3u8#第03集$http://shishang.dingxiangzuida.com/20200429/507_65c75f08/index.m3u8$zuidam3u8#第04集$http://shishang.dingxiangzuida.com/20200429/506_9fc18452/index.m3u8$zuidam3u8#第05集$http://shishang.dingxiangzuida.com/20200429/505_d2c2f4a9/index.m3u8$zuidam3u8#第06集$http://shishang.dingxiangzuida.com/20200429/504_2e4cbaff/index.m3u8$zuidam3u8#第07集$http://shishang.dingxiangzuida.com/20200429/503_d642d822/index.m3u8$zuidam3u8#第08集$http://shishang.dingxiangzuida.com/20200429/502_e0970303/index.m3u8$zuidam3u8#第09集$http://shishang.dingxiangzuida.com/20200429/501_6334e9cb/index.m3u8$zuidam3u8#第10集$http://shishang.dingxiangzuida.com/20200429/500_4ca54181/index.m3u8$zuidam3u8#第11集$http://shishang.dingxiangzuida.com/20200429/499_46d016bc/index.m3u8$zuidam3u8#第12集$http://shishang.dingxiangzuida.com/20200429/498_0500462b/index.m3u8$zuidam3u8#第13集$http://shishang.dingxiangzuida.com/20200429/497_a9a2e72c/index.m3u8$zuidam3u8#第14集$http://shishang.dingxiangzuida.com/20200429/496_89a7245f/index.m3u8$zuidam3u8#第15集$http://shishang.dingxiangzuida.com/20200429/495_15d99287/index.m3u8$zuidam3u8#第16集$http://shishang.dingxiangzuida.com/20200429/494_7ef7c260/index.m3u8$zuidam3u8#第17集$http://shishang.dingxiangzuida.com/20200429/493_e563e521/index.m3u8$zuidam3u8#第18集$http://shishang.dingxiangzuida.com/20200429/492_242f68b9/index.m3u8$zuidam3u8#第19集$http://shishang.dingxiangzuida.com/20200429/491_8fd89fe8/index.m3u8$zuidam3u8#第20集$http://shishang.dingxiangzuida.com/20200429/490_2687c928/index.m3u8$zuidam3u8#第21集$http://shishang.dingxiangzuida.com/20200429/489_56fd4dab/index.m3u8$zuidam3u8#第22集$http://shishang.dingxiangzuida.com/20200429/488_9d7b1ec4/index.m3u8$zuidam3u8#第23集$http://shishang.dingxiangzuida.com/20200429/487_a9cda148/index.m3u8$zuidam3u8#第24集$http://shishang.dingxiangzuida.com/20200429/486_7c30d132/index.m3u8$zuidam3u8#第25集$http://shishang.dingxiangzuida.com/20200429/485_903e53ad/index.m3u8$zuidam3u8#第26集$http://shishang.dingxiangzuida.com/20200429/484_79729567/index.m3u8$zuidam3u8#第27集$http://shishang.dingxiangzuida.com/20200429/483_89537f9e/index.m3u8$zuidam3u8#第28集$http://shishang.dingxiangzuida.com/20200429/482_2138ab87/index.m3u8$zuidam3u8#第29集$http://shishang.dingxiangzuida.com/20200429/481_7a2819d0/index.m3u8$zuidam3u8#第30集$http://shishang.dingxiangzuida.com/20200429/480_64d529d9/index.m3u8$zuidam3u8#第31集$http://shishang.dingxiangzuida.com/20200429/479_2c780920/index.m3u8$zuidam3u8#第32集$http://shishang.dingxiangzuida.com/20200429/478_b38c59a4/index.m3u8$zuidam3u8#第33集$http://shishang.dingxiangzuida.com/20200429/477_3cceff86/index.m3u8$zuidam3u8#第34集$http://shishang.dingxiangzuida.com/20200429/476_b17176d0/index.m3u8$zuidam3u8#第35集$http://shishang.dingxiangzuida.com/20200429/475_b4fd25c1/index.m3u8$zuidam3u8#第36集$http://shishang.dingxiangzuida.com/20200429/474_2e89a87b/index.m3u8$zuidam3u8#第37集$http://shishang.dingxiangzuida.com/20200429/473_673047be/index.m3u8$zuidam3u8#第38集$http://shishang.dingxiangzuida.com/20200429/472_8e97e874/index.m3u8$zuidam3u8#第39集$http://shishang.dingxiangzuida.com/20200429/471_5f51eb05/index.m3u8$zuidam3u8#第40集$http://shishang.dingxiangzuida.com/20200429/470_78852215/index.m3u8$zuidam3u8#第41集$http://shishang.dingxiangzuida.com/20200429/469_abb0e335/index.m3u8$zuidam3u8#第42集$http://shishang.dingxiangzuida.com/20200429/468_b5d913c3/index.m3u8$zuidam3u8#第43集$http://shishang.dingxiangzuida.com/20200429/467_fd0ba83a/index.m3u8$zuidam3u8"}}, "des": "1931年“九一八”日寇强占我东北，企图利用东北丰富的战争资源，实现它吞灭中国，统治世界的野心。中华民族也因此进入了一段黑暗期。但中华民族是一个不畏强权，为了自由不怕牺牲的民族，在中国共产党的领导下，全国各民族、各阶级、各党派团结一致结成了全民抗日统一战线，开始了付出巨大牺牲、艰苦卓绝的抗日战争。 《硬骨头》依托这段真实的历史背景，讲述了一个不为人知的抗战故事。中华民族每到民族危亡时刻，总有一些硬骨头挺身而出，朔风凌冽，大雪飞扬的黑土地上就活跃着抗联一支特别武装——抗联雪狼尖刀队，这群硬骨头在白山黑水、林海雪原中出死入生，携手共赴国难已经十四年，他们从未屈服，从未停止过战斗，他们让日本人闻风丧胆。他们即将迎来胜利的曙光。《硬骨头》中的这群硬骨头，心中只有一个信念，中华民族不可辱，中华儿女不可欺。 末日临近，日本关东军不甘心失败，企图做垂死挣扎，他们的救命稻草是中苏边境线上秘密修筑的十七处军事要塞，号称“东方马奇诺防线”，这些要塞是苏联红军大反攻的最大障碍，不侦查清楚，会产生巨大牺牲，为了减少牺牲，就要获取日军要塞兵力部署图。这是一个难以完成的终极任务。我们的英雄，雪狼尖刀队队长杨子良主动请缨，要啃下这块硬骨头。一场铁血战士以命相搏与敌硬碰硬的殊死较量随之展开……"}, {"last": "2020-04-29 14:57:22", "id": "84743", "tid": "10", "name": "暴裂风雷道", "type": "剧情片", "pic": "https://tu.tianzuida.com/pic/upload/vod/2020-04-29/202004291588133845.jpg", "lang": "国语", "area": "大陆", "year": "2020", "state": "0", "note": "HD1280高清国语中字版", "actor": "张文,张晓晨,周阶,陈彤民,项毅,李艺轩,马丽", "director": "张文", "dl": {"dd": {"@flag": "zuidam3u8", "#text": "HD1280高清国语中字版$http://yuledy.helanzuida.com/20200429/3230_6e99ac58/index.m3u8$zuidam3u8"}}, "des": "农村小伙秦风来到南都市打工，想让师傅过上好日子，不料，却在南都发现自己的亲哥哥是东皇集团的少主。在集团领袖曹世清失踪之后，东皇集团内部动荡。曹雷在集团中受到来自二叔曹世杰的压力，曹世杰为打压曹雷，将秦风也卷入了纷争之中……"}, {"last": "2020-04-29 13:10:52", "id": "84744", "tid": "10", "name": "我的黑色小礼服", "type": "剧情片", "pic": "https://tu.tianzuida.com/pic/upload/vod/2020-04-29/202004291588137008.jpg", "lang": "韩语", "area": "韩国", "year": "2011", "state": "0", "note": "BD超清中字", "actor": "尹恩惠,朴寒星,刘仁娜,车艺莲,申东浩,高昌锡 Chang-Seok Ko", "director": "许仁茂", "dl": {"dd": {"@flag": "zuidam3u8", "#text": "BD超清中字$http://iqiyi.zuidameiju.com/20200428/15159_35c17b06/index.m3u8$zuidam3u8"}}, "des": "毕业季，四个名牌大学表演系的闺蜜各自憧憬着进入社会的生活。慧智（朴韩星 饰）整天花天酒地美容美甲，忽悠大家及时行乐，却无意中成了广告红人。柳敏（尹恩惠 饰）决定跟师兄男友分手，原因是后者的小气和小心眼，在慧智的介绍下，她认识了富二代，并且找到了一份电视台助理的工作，并偶然遇见了中学的粉丝，彼此倾吐对工作的感受。秀珍（车艺莲 饰）处心积虑想做演员，可惜在屡屡受挫，待业的她偷偷篡改了学历为了获得家教的职位。敏姬（刘仁娜 饰）懒得看父母冷战到离异的杯具，决定上补习班拯救烂的要命的英语，却没想到遇到了一个冤家学弟。四个姐妹，分别遭遇了人生之中新的抉择和挑战，当爱情、事业向友谊挑衅的时候，她们又会如何应对……"}, {"last": "2020-04-29 13:13:32", "id": "84745", "tid": "10", "name": "我生命中最美丽的一周", "type": "剧情片", "pic": "https://tu.tianzuida.com/pic/upload/vod/2020-04-29/202004291588137122.jpg", "lang": "韩语", "area": "韩国", "year": "2005", "state": "0", "note": "BD高清中字", "actor": "黄政民,任昌丁,严正化,金裕贞,吴美熙,郑京浩", "director": "闵奎东", "dl": {"dd": {"@flag": "zuidam3u8", "#text": "BD高清中字$http://iqiyi.zuidameiju.com/20200428/15160_ef4b1851/index.m3u8$zuidam3u8"}}, "des": "影片由六段相互独立又彼此相关的爱之故事组成，描写了六对来自不同背景、有着不同经历的男女，在一个星期内度过的最美时光。 第一个故事是关于夕阳之爱，第二个故事则讲述了贫苦夫妻间的爱情故事，第三个故事是关于父女之间的爱的故事，第四个故事描绘了父子之间的爱和同性男人之间的情感，第五个故事则围绕一个大龄单身男警察与成熟离异女医生之间展开，第六个故事刻画了一个修女与一个知名流行歌手之间的爱情故事。六段独特的故事彼此穿插交织，又各自独立完整。在爱的世界中，生活正在一如既往的前行，酸甜苦辣，尽在其中。"}, {"last": "2020-04-29 13:15:47", "id": "84746", "tid": "10", "name": "喜马拉亚星", "type": "剧情片", "pic": "https://tu.tianzuida.com/pic/upload/vod/2020-04-29/202004291588137272.jpg", "lang": "粤语", "area": "香港", "year": "2005", "state": "0", "note": "BD高清粤语", "actor": "郑中基,张柏芝,刘青云,应采儿,吴镇宇,黄又南,徐天佑,李兆基,黄光亮,成奎安", "director": "韦家辉", "dl": {"dd": {"@flag": "zuidam3u8", "#text": "BD高清粤语$http://iqiyi.zuidameiju.com/20200428/15161_f5820664/index.m3u8$zuidam3u8"}}, "des": "在喜玛拉雅山长大的亚星（郑中基）练有一身瑜伽好功夫，某日奉父母之命下山参加印度西施家族举办的瑜伽选夫比赛的途中，被恨嫁的大家姐（应采儿）缠住。为了阻止亚星参加比赛，大家姐想出把他变成人见人厌的坏小子的狠招，不想联合三大恶人也没能将亚星改变，不甘心之下，大家姐又找来以坏混世的大胆叔叔（吴镇宇）。 可惜大胆叔叔与朋友惊青舅父（刘青云）及其两个外甥已不幸被印度催眠术催眠，连自己是谁都不再晓得，然而亚星总算找到了领门人，赌场的两头神蛇把他教成了沉迷于赌博和吸毒的坏小子，此时，大家姐发现还是原来的亚星比较好，决定陪其一同喝下“印度神奇油”回到从前。"}, {"last": "2020-04-29 13:20:04", "id": "84747", "tid": "6", "name": "熊出没注意", "type": "喜剧片", "pic": "https://tu.tianzuida.com/pic/upload/vod/2020-04-29/202004291588137460.jpg", "lang": "国语", "area": "大陆", "year": "2010", "state": "0", "note": "BD超清中字", "actor": "李晨,尚雯婕,李乃文", "director": "程樯", "dl": {"dd": {"@flag": "zuidam3u8", "#text": "BD超清中字$http://iqiyi.zuidameiju.com/20200428/15162_1730bb7e/index.m3u8$zuidam3u8"}}, "des": "乐珊珊（尚雯婕 饰）是演艺圈里一颗冉冉升起的新星，天性崇尚自由的乐珊珊不满意于经纪公司填鸭式的活动安排，和经纪人之间产生了矛盾，一怒之下，乐珊珊上演了“离家出走”的戏码，只身一人来到风景秀丽的江南小镇，决定在这里给自己好好放一个假。 期间，乐珊珊结识了名不见经传的落魄画家沙立（李晨 饰），两人在误打误撞之中救下了一只小熊，两人遂扮演起了“熊爸”和“熊妈”的角色，精心照料和保护着小熊。镇上出现了四个神秘男子，他们四处探访寻查，只为找到小熊的下落，他们四人的目标十分明确，那就是活捉小熊，活取熊胆！"}]}}}